{"period":"2017-07","ranking":{"summary":{"tags":[{"name":"Python","value":210},{"name":"开发","value":183},{"name":"App","value":150},{"name":"Java","value":148},{"name":"Android","value":118},{"name":"PHP","value":99},{"name":"域名","value":96},{"name":"熟悉","value":93},{"name":"iOS","value":92},{"name":"Google","value":88},{"name":"Mac","value":85},{"name":"V2EX","value":77},{"name":"MacBook","value":69},{"name":"微信","value":69},{"name":"程序员","value":69},{"name":"代码","value":68},{"name":"GitHub","value":65},{"name":"QQ","value":63},{"name":"文件","value":63},{"name":"服务器","value":63}],"nodes":[{"name":"qna","value":1550},{"name":"all4all","value":662},{"name":"jobs","value":545},{"name":"programmer","value":392},{"name":"share","value":260},{"name":"python","value":229},{"name":"chamber","value":156},{"name":"gts","value":149},{"name":"create","value":130},{"name":"bb","value":127},{"name":"flood","value":127},{"name":"apple","value":122},{"name":"android","value":121},{"name":"promotions","value":102},{"name":"cv","value":99},{"name":"career","value":98},{"name":"flamewar","value":88},{"name":"pointless","value":86},{"name":"macos","value":80},{"name":"php","value":66}],"members":[{"name":"guyeuro","value":33},{"name":"xoxo419","value":22},{"name":"saximi","value":21},{"name":"ajeef","value":20},{"name":"StanMarsh","value":20},{"name":"Tunar","value":18},{"name":"a251922581","value":16},{"name":"hoythan","value":16},{"name":"qq12345454","value":16},{"name":"bytedance","value":15},{"name":"NonClockworkChen","value":15},{"name":"beyoung","value":14},{"name":"Event","value":14},{"name":"gdtv","value":14},{"name":"hunter5am","value":14},{"name":"Jacky001","value":14},{"name":"pythonee","value":14},{"name":"dou4cc","value":13},{"name":"permaylau","value":13},{"name":"zyllwy","value":13}],"activity":{"authors":[4046,3996,3676],"commenters":[13235,12764,11395]}},"posts":[{"id":379097,"title":"高龄程序员不完全肉身敏感词指南和经验分享","node":"share","create_at":1501426261,"clicks":7104,"reply_count":96,"favorite_count":222,"thank_count":44,"votes":29,"author":"winterock","score":1048.869},{"id":377051,"title":"关于 UCloud 赖账的 10 万 推广费，想请大家评评理","node":"gts","create_at":1500629906,"clicks":50280,"reply_count":526,"favorite_count":54,"thank_count":6,"votes":56,"author":"jellybool","score":840.825},{"id":376495,"title":"近期发生的，大家比较关心的，翻 wa11，被喝茶","node":"shadowsocks","create_at":1500463421,"clicks":32220,"reply_count":214,"favorite_count":167,"thank_count":5,"votes":30,"author":"oplang","score":810.38},{"id":376057,"title":"Mac 开发的神秘面纱：后娘养的嫡长子","node":"programmer","create_at":1500336322,"clicks":16378,"reply_count":118,"favorite_count":154,"thank_count":24,"votes":24,"author":"quietjosen","score":757.704},{"id":378748,"title":"要不每人说一个绝赞的 Linux 命令工具?","node":"linux","create_at":1501260764,"clicks":17642,"reply_count":160,"favorite_count":170,"thank_count":2,"votes":2,"author":"Immortal","score":693.778},{"id":378730,"title":"除了\tBootstrap，还有什么前端框架能让毫无美感的程序员轻松搭出好看的网页？","node":"qna","create_at":1501255023,"clicks":14706,"reply_count":45,"favorite_count":206,"thank_count":4,"votes":0,"author":"solomaster","score":692.596},{"id":379088,"title":"\"同类软件的鼻祖” Seer 抄走了我的 GPL 代码去卖钱……","node":"programmer","create_at":1501423357,"clicks":26714,"reply_count":158,"favorite_count":95,"thank_count":20,"votes":58,"author":"xupefei","score":669.193},{"id":372880,"title":"港真, 这个年龄和状态, 该出国读个研吗?","node":"programmer","create_at":1499138441,"clicks":22075,"reply_count":206,"favorite_count":136,"thank_count":3,"votes":2,"author":"LuciferMoo","score":643.002},{"id":373901,"title":"入职一周 写点体会 拉点仇恨 有图有真相","node":"programmer","create_at":1499485144,"clicks":34536,"reply_count":375,"favorite_count":63,"thank_count":4,"votes":0,"author":"beyoung","score":594.45},{"id":379031,"title":"顺丰到付，送几本《 Python 地理空间分析指南（第 2 版）》","node":"free","create_at":1501405532,"clicks":11138,"reply_count":536,"favorite_count":10,"thank_count":1,"votes":0,"author":"clink8001","score":580.318},{"id":377223,"title":"分享一个自己用 PHP 写的豆瓣妹子图爬虫，每日更新！","node":"programmer","create_at":1500713084,"clicks":14218,"reply_count":91,"favorite_count":140,"thank_count":9,"votes":1,"author":"wyan453351466","score":567.562},{"id":379172,"title":"免费来领 1 个月摩拜单车月卡了，可与上次 5 元 3 个月月卡叠加。","node":"deals","create_at":1501469126,"clicks":13199,"reply_count":129,"favorite_count":7,"thank_count":76,"votes":11,"author":"c0mmand","score":561.488},{"id":378173,"title":"查询自己 QQ 号码注册的具体时间","node":"share","create_at":1501067633,"clicks":18277,"reply_count":168,"favorite_count":106,"thank_count":7,"votes":0,"author":"crab","score":530.813},{"id":379103,"title":"美区 Apple ID 成功绑定美区 PayPal 并使用国内银行卡消费","node":"apple","create_at":1501428242,"clicks":114009,"reply_count":170,"favorite_count":99,"thank_count":2,"votes":0,"author":"codex","score":488.644},{"id":377158,"title":"UCloud 关于 Laravist 社区事件的说明","node":"gts","create_at":1500693449,"clicks":36048,"reply_count":407,"favorite_count":17,"thank_count":0,"votes":0,"author":"wxxshu","score":468.493},{"id":378248,"title":"有没有炒港股和美股的，香港银行开户怎么开？","node":"invest","create_at":1501119679,"clicks":32748,"reply_count":229,"favorite_count":75,"thank_count":0,"votes":0,"author":"univfun","score":464.397},{"id":376443,"title":"程序员想自学一门乐器，入门容易点，有什么推荐的？","node":"programmer","create_at":1500452649,"clicks":31227,"reply_count":246,"favorite_count":64,"thank_count":1,"votes":0,"author":"Acheron","score":453.349},{"id":372462,"title":"支付宝《花呗》新版合同，让人不寒而栗，都要搜集“手机通话分钟数了”","node":"alipay","create_at":1498969105,"clicks":51290,"reply_count":237,"favorite_count":58,"thank_count":0,"votes":11,"author":"Pagani","score":443.845},{"id":377939,"title":"最长寿、石器时代的中文网站，有哪些？","node":"qna","create_at":1500992018,"clicks":13025,"reply_count":134,"favorite_count":86,"thank_count":4,"votes":0,"author":"hematite","score":421.475},{"id":377060,"title":"UBNT 高端无线路由器 AmpliFi 团购活动——V2EX 网友专享！","node":"ubnt","create_at":1500631436,"clicks":40665,"reply_count":180,"favorite_count":65,"thank_count":3,"votes":0,"author":"Ubiquiti","score":400.613},{"id":377944,"title":"第一次玩爬虫有点上瘾啊，写了个百度云资源搜索。。","node":"create","create_at":1500993434,"clicks":17545,"reply_count":77,"favorite_count":94,"thank_count":6,"votes":0,"author":"huangzitao","score":398.773},{"id":375275,"title":"大家都来说说你最喜欢的名人名言","node":"qna","create_at":1500000882,"clicks":14734,"reply_count":194,"favorite_count":51,"thank_count":6,"votes":0,"author":"yylzcom","score":386.598},{"id":379047,"title":"把前两天那个博弈论的游戏翻译成了中文版 - 信任的进化","node":"create","create_at":1501410507,"clicks":23954,"reply_count":34,"favorite_count":75,"thank_count":17,"votes":9,"author":"Yvette","score":372.084},{"id":375186,"title":"分享自用代理工具 - glider","node":"share","create_at":1499956307,"clicks":11071,"reply_count":58,"favorite_count":92,"thank_count":3,"votes":4,"author":"nadoo","score":366.312},{"id":373158,"title":"国外的程序员都是什么样的状态？","node":"programmer","create_at":1499223813,"clicks":18453,"reply_count":85,"favorite_count":83,"thank_count":0,"votes":4,"author":"nana6","score":351.823},{"id":376710,"title":"破解有道翻译反爬虫机制","node":"pointless","create_at":1500536528,"clicks":2815,"reply_count":36,"favorite_count":85,"thank_count":7,"votes":4,"author":"CicadaMan","score":341.943},{"id":374908,"title":"程序员做些个人项目，发现最难的还是找准需求啊","node":"programmer","create_at":1499872013,"clicks":9041,"reply_count":45,"favorite_count":93,"thank_count":0,"votes":0,"author":"fwee","score":333.11},{"id":378841,"title":"吐槽一下国行 Surfacebook，微软售后以及京东商城；以及对之前在 V2 推荐别人购买 Surfacebook 的行为表示歉意！！","node":"gts","create_at":1501313163,"clicks":28757,"reply_count":150,"favorite_count":32,"thank_count":9,"votes":13,"author":"kouryu","score":327.267},{"id":372893,"title":"选择继续在美国工作还是回国工作？","node":"career","create_at":1499140745,"clicks":22240,"reply_count":182,"favorite_count":39,"thank_count":1,"votes":0,"author":"moonqqqq","score":314.01},{"id":376651,"title":"问一下，混淆过的协议现在检测率有多少？","node":"shadowsocks","create_at":1500524907,"clicks":37257,"reply_count":29,"favorite_count":89,"thank_count":0,"votes":0,"author":"QAPTEAWH","score":306.526},{"id":376024,"title":"你们一般都爬些什么？","node":"python","create_at":1500303219,"clicks":10902,"reply_count":60,"favorite_count":75,"thank_count":1,"votes":0,"author":"julyclyde","score":299.297},{"id":374721,"title":"我翻译的《数字视频介绍》得到了原作者的认可，被接受为官方项目的一部分啦。","node":"create","create_at":1499829774,"clicks":5924,"reply_count":61,"favorite_count":58,"thank_count":9,"votes":5,"author":"archimboldi","score":298.687},{"id":374824,"title":"步入社会，一些事情和疑问必须要问出来，否则无心敲代码","node":"career","create_at":1499848189,"clicks":15561,"reply_count":167,"favorite_count":39,"thank_count":1,"votes":0,"author":"caijihui11","score":298.653},{"id":375658,"title":"对工作失去了热情...一点感想","node":"career","create_at":1500142554,"clicks":11258,"reply_count":73,"favorite_count":63,"thank_count":5,"votes":0,"author":"qoras","score":296.329},{"id":374418,"title":"在 iPic 周岁时，说说这款让我骄傲的产品","node":"create","create_at":1499737130,"clicks":14333,"reply_count":103,"favorite_count":37,"thank_count":14,"votes":0,"author":"quietjosen","score":293.57},{"id":378822,"title":"中国区的账号要怎样才能转换成美国区的账号？","node":"ios","create_at":1501305577,"clicks":36908,"reply_count":157,"favorite_count":40,"thank_count":1,"votes":0,"author":"travelforlove","score":292.516},{"id":372829,"title":"Klib 到底赚了多少钱？","node":"create","create_at":1499128834,"clicks":9538,"reply_count":89,"favorite_count":47,"thank_count":10,"votes":0,"author":"quietjosen","score":289.163},{"id":376899,"title":"vultr 日本区仍可以创建 2.5 刀的实例","node":"vps","create_at":1500603733,"clicks":7599,"reply_count":102,"favorite_count":42,"thank_count":8,"votes":6,"author":"neosfung","score":288.936},{"id":376429,"title":"百度网盘会员有什么渠道买便宜点吗？发现现在不用会员根本没速度。。","node":"share","create_at":1500450266,"clicks":33653,"reply_count":61,"favorite_count":72,"thank_count":0,"votes":0,"author":"revival83","score":287.424},{"id":372550,"title":"airAnime - 一款不错的聚合动漫搜索程序","node":"create","create_at":1499002574,"clicks":9581,"reply_count":42,"favorite_count":69,"thank_count":3,"votes":5,"author":"TriiHsia","score":283.168},{"id":378165,"title":"联通与工商银行合作的套餐：梦想 E 卡， 19 元 2GB","node":"share","create_at":1501065381,"clicks":29410,"reply_count":124,"favorite_count":46,"thank_count":2,"votes":0,"author":"lihua","score":282.289},{"id":374395,"title":"麻痹，黑马培训机构的学员写的代码！真爱生命远离培训班！！！","node":"programmer","create_at":1499710607,"clicks":39029,"reply_count":175,"favorite_count":30,"thank_count":0,"votes":0,"author":"chendown","score":275.572},{"id":374778,"title":"图解 TCP 三次握手与四次挥手","node":"linux","create_at":1499840036,"clicks":7828,"reply_count":44,"favorite_count":68,"thank_count":3,"votes":1,"author":"enocher","score":273.966},{"id":374067,"title":"空调品牌哪个好一点？","node":"life","create_at":1499579147,"clicks":16516,"reply_count":133,"favorite_count":42,"thank_count":0,"votes":0,"author":"pzzrudlf","score":268.712},{"id":374056,"title":"使用 Python 快速进行物联网开发-只要五十元","node":"python","create_at":1499574708,"clicks":16305,"reply_count":66,"favorite_count":61,"thank_count":2,"votes":0,"author":"hat4","score":268.699},{"id":375011,"title":"你们平均一天睡多长时间,状态怎么样？","node":"programmer","create_at":1499917537,"clicks":16812,"reply_count":171,"favorite_count":26,"thank_count":0,"votes":0,"author":"yasumoto","score":258.73},{"id":373389,"title":"Linux 笔记本求推荐（预算 5000 左右）","node":"linux","create_at":1499305264,"clicks":26181,"reply_count":196,"favorite_count":15,"thank_count":1,"votes":0,"author":"ray1888","score":256.173},{"id":377413,"title":"分享一下自己做的一个地图找租房的网站....","node":"create","create_at":1500822842,"clicks":11231,"reply_count":62,"favorite_count":56,"thank_count":3,"votes":0,"author":"codelover2016","score":254.327},{"id":377725,"title":"我对 Python 的困惑","node":"programmer","create_at":1500945094,"clicks":20532,"reply_count":160,"favorite_count":28,"thank_count":0,"votes":0,"author":"assad","score":253.93},{"id":378264,"title":"感觉自己好穷。。。只能努力工作","node":"life","create_at":1501122433,"clicks":12465,"reply_count":83,"favorite_count":50,"thank_count":0,"votes":5,"author":"WuHaaaaaaa","score":252.431},{"id":378500,"title":"wechat-admin: 通过 Web 管理微信和微信机器人","node":"python","create_at":1501199247,"clicks":6214,"reply_count":25,"favorite_count":66,"thank_count":2,"votes":5,"author":"dongweiming","score":251.735},{"id":372589,"title":"怎么开始动手自己写一个编译器，编译器的理论学习该从何处下手？","node":"programmer","create_at":1499046448,"clicks":8689,"reply_count":29,"favorite_count":71,"thank_count":0,"votes":0,"author":"pythonee","score":251.07},{"id":377712,"title":"说说我出道后的处女作：剪贴板神器 iPaste","node":"create","create_at":1500941178,"clicks":10927,"reply_count":75,"favorite_count":46,"thank_count":4,"votes":3,"author":"quietjosen","score":248.299},{"id":374638,"title":"很讨厌那种站电梯上挡住路的人","node":"qna","create_at":1499787225,"clicks":13511,"reply_count":194,"favorite_count":13,"thank_count":0,"votes":1,"author":"qui9090","score":244.511},{"id":374258,"title":"这种明目张胆的盗版书 Github repo 怎么怼","node":"programmer","create_at":1499668264,"clicks":21747,"reply_count":123,"favorite_count":37,"thank_count":0,"votes":0,"author":"zhengxiaowai","score":243.987},{"id":378239,"title":"你的电脑杀毒软件装的是哪个款式?","node":"programmer","create_at":1501117273,"clicks":16867,"reply_count":172,"favorite_count":20,"thank_count":0,"votes":1,"author":"xoxo419","score":243.733},{"id":378509,"title":"所以，还是免费开放注册吧","node":"create","create_at":1501203590,"clicks":11860,"reply_count":92,"favorite_count":43,"thank_count":2,"votes":1,"author":"AlwaysBee","score":242.381},{"id":372961,"title":"手摸手，带你用 vue 撸后台 系列四(vueAdmin 一个极简的后台基础模板)","node":"programmer","create_at":1499153124,"clicks":21496,"reply_count":14,"favorite_count":64,"thank_count":4,"votes":3,"author":"PanJiaChen","score":241.976},{"id":379407,"title":"又被小米浏览器强奸了--卿本佳人，奈何作贼？","node":"gts","create_at":1501514749,"clicks":23590,"reply_count":206,"favorite_count":5,"thank_count":2,"votes":0,"author":"tamlok","score":241.069},{"id":378511,"title":"说实话，现在做网站还能赚钱吗？能否实现财务自由？","node":"internet","create_at":1501204085,"clicks":17483,"reply_count":83,"favorite_count":49,"thank_count":0,"votes":0,"author":"aixin2019","score":239.769},{"id":378811,"title":"部分使用 Network Extension 功能的 app 在国区被下架","node":"ios","create_at":1501302458,"clicks":29113,"reply_count":113,"favorite_count":35,"thank_count":0,"votes":5,"author":"goodbest","score":238.279},{"id":377734,"title":"你们去星爸爸都点哪一种喝，尝试了一下冷萃，真难喝","node":"coffee","create_at":1500947982,"clicks":22961,"reply_count":136,"favorite_count":30,"thank_count":0,"votes":1,"author":"t2doo","score":238.042},{"id":377861,"title":"学习 Linux 应该怎么入手？","node":"newbie","create_at":1500972552,"clicks":4749,"reply_count":110,"favorite_count":39,"thank_count":0,"votes":1,"author":"HeroTop","score":237.466},{"id":374344,"title":"严肃问个问题，为什么年轻程序员中，喜好二次元文化的比例这么高？ 百思不得其解…","node":"qna","create_at":1499684562,"clicks":21732,"reply_count":153,"favorite_count":23,"thank_count":1,"votes":0,"author":"Owis","score":236.987},{"id":376351,"title":"淘宝随意永久封号，说是安全风险","node":"gts","create_at":1500432443,"clicks":28670,"reply_count":174,"favorite_count":13,"thank_count":1,"votes":4,"author":"pupboss","score":236.264},{"id":377449,"title":"写了个短信转发的安卓小程序","node":"create","create_at":1500861544,"clicks":12017,"reply_count":43,"favorite_count":57,"thank_count":2,"votes":0,"author":"autosquid","score":233.394},{"id":375610,"title":"罗永浩 Big Bang 被指抄袭效仿 Pin","node":"flamewar","create_at":1500120165,"clicks":7991,"reply_count":177,"favorite_count":15,"thank_count":0,"votes":0,"author":"thinkSky","score":230.986},{"id":379176,"title":"为什么大多数公司随着业务的增长技术栈都转向 Java 了？","node":"programmer","create_at":1501469668,"clicks":22563,"reply_count":125,"favorite_count":30,"thank_count":0,"votes":1,"author":"assad","score":227.024},{"id":372924,"title":"心态炸了怎么调整","node":"programmer","create_at":1499148535,"clicks":15518,"reply_count":141,"favorite_count":22,"thank_count":2,"votes":0,"author":"xiaojunjor","score":226.65},{"id":376061,"title":"做调查，看看搞技术的都喜欢开什么车？","node":"car","create_at":1500337733,"clicks":13782,"reply_count":184,"favorite_count":11,"thank_count":0,"votes":0,"author":"cnqncom","score":226.531},{"id":374201,"title":"感觉我们公司测试真能测试，写一个小功能都可以提出 57 个 bug...","node":"programmer","create_at":1499655141,"clicks":22532,"reply_count":154,"favorite_count":17,"thank_count":1,"votes":3,"author":"yasumoto","score":226.023},{"id":372657,"title":"如果没有家庭压力，你愿不愿意一边撸码一边周游世界？","node":"programmer","create_at":1499058520,"clicks":14759,"reply_count":150,"favorite_count":22,"thank_count":0,"votes":0,"author":"Reign","score":225.6},{"id":377419,"title":"学习编程应该购买哪一款电脑？ MBP 还是 New SP？","node":"programmer","create_at":1500827605,"clicks":26123,"reply_count":188,"favorite_count":9,"thank_count":0,"votes":0,"author":"loinway","score":225.171},{"id":374826,"title":"大家如何看待学校宿舍没有空调，今天母校在知乎火了一把","node":"qna","create_at":1499848443,"clicks":20443,"reply_count":176,"favorite_count":13,"thank_count":0,"votes":0,"author":"aaronzjw","score":224.925},{"id":375151,"title":"[上海] [小红书] 资深后端工程师 [20K - 30K] (3 ~ 5 年经验)","node":"jobs","create_at":1499946555,"clicks":19326,"reply_count":113,"favorite_count":23,"thank_count":0,"votes":16,"author":"junhao","score":223.869},{"id":373635,"title":"公司来了个想总经理,我该何去何从?","node":"career","create_at":1499390351,"clicks":16788,"reply_count":152,"favorite_count":19,"thank_count":0,"votes":0,"author":"ugugzh","score":218.728},{"id":378113,"title":"it 公司趣事多，分享分享这些年听说或者遇到的 IT 业界趣事","node":"programmer","create_at":1501055331,"clicks":15796,"reply_count":125,"favorite_count":28,"thank_count":0,"votes":0,"author":"xuezher","score":218.668},{"id":376138,"title":"在彻底翻车前，现在可以做些什么来保证车祸后正常使用 Gmail？","node":"flamewar","create_at":1500353096,"clicks":10063,"reply_count":122,"favorite_count":29,"thank_count":0,"votes":0,"author":"YyYyYyy","score":218.217},{"id":378142,"title":"这就是蛋壳公寓，牛逼的蟑螂公寓","node":"flamewar","create_at":1501060074,"clicks":23530,"reply_count":147,"favorite_count":17,"thank_count":1,"votes":2,"author":"yunhui","score":217.066},{"id":374364,"title":"如何消除肚子上的赘肉？","node":"qna","create_at":1499694378,"clicks":7733,"reply_count":75,"favorite_count":44,"thank_count":0,"votes":0,"author":"imeradio","score":215.953},{"id":376825,"title":"苦尽甘来","node":"programmer","create_at":1500560609,"clicks":16515,"reply_count":152,"favorite_count":7,"thank_count":6,"votes":0,"author":"moyang","score":212.712},{"id":375934,"title":"除了沉浸代码兴趣之中, 还有其它什么兴趣爱好?","node":"programmer","create_at":1500280188,"clicks":13914,"reply_count":126,"favorite_count":25,"thank_count":0,"votes":1,"author":"xoxo419","score":212.541},{"id":377321,"title":"分享一个电视看油管神器，自带谷歌账号系统，支持手机推送","node":"share","create_at":1500779886,"clicks":8252,"reply_count":9,"favorite_count":59,"thank_count":3,"votes":0,"author":"xiusedelang","score":210.018},{"id":378546,"title":"10 年前","node":"random","create_at":1501209864,"clicks":8605,"reply_count":73,"favorite_count":25,"thank_count":10,"votes":0,"author":"cocacold","score":207.06},{"id":376335,"title":"如何做一个有上进心的 PHP 开发，怎样才能补全自身后端技术知识面？","node":"php","create_at":1500429972,"clicks":9938,"reply_count":59,"favorite_count":46,"thank_count":0,"votes":0,"author":"andy009","score":206.204},{"id":375831,"title":"想转行 IT 行业，有什么建议吗？还有做哪一块比较有前途？","node":"career","create_at":1500256992,"clicks":22390,"reply_count":118,"favorite_count":26,"thank_count":0,"votes":0,"author":"very0576","score":206.016},{"id":376552,"title":"啥话不说，自己看图","node":"shadowsocks","create_at":1500483021,"clicks":7513,"reply_count":90,"favorite_count":35,"thank_count":0,"votes":0,"author":"15015613","score":203.925},{"id":373222,"title":"还有能跟阿里云国际版香港 200M 抗衡的 VPS 吗？","node":"bb","create_at":1499237714,"clicks":46997,"reply_count":109,"favorite_count":28,"thank_count":0,"votes":0,"author":"Junghh","score":203.758},{"id":375007,"title":"中国区 Apple ID 的 iCloud 将迁到贵州数据中心，大家怎么看？","node":"apple","create_at":1499916575,"clicks":15959,"reply_count":149,"favorite_count":14,"thank_count":0,"votes":1,"author":"panamera","score":202.678},{"id":376960,"title":"黑域作者正在搞两个非常赛艇的东西","node":"android","create_at":1500612195,"clicks":37044,"reply_count":114,"favorite_count":26,"thank_count":0,"votes":0,"author":"kamen","score":202.52},{"id":373781,"title":"离 Nim 1.0 正式版发布不远了，官方论坛说，基本上以现在 0.17.0 为语法雏形，语法不再大改动了,要改也改 bug 和编译 y 引擎了,四大用户群 Python 、C、Pascal、javascript 都不放过。","node":"programmer","create_at":1499419216,"clicks":9256,"reply_count":31,"favorite_count":50,"thank_count":2,"votes":1,"author":"ajeef","score":202.133},{"id":375329,"title":"这两天各大互联网公司是不是都在急招 AC 自动机工程师？","node":"programmer","create_at":1500010794,"clicks":16095,"reply_count":113,"favorite_count":26,"thank_count":0,"votes":0,"author":"Morriaty","score":200.686},{"id":378645,"title":"你们都是做了些什么网站！！！","node":"webmaster","create_at":1501228171,"clicks":9807,"reply_count":59,"favorite_count":44,"thank_count":0,"votes":0,"author":"micookie","score":200.191},{"id":376894,"title":"免费领取 Steam 影子武士，就在 HumbleBunle 商店","node":"steam","create_at":1500603017,"clicks":9792,"reply_count":73,"favorite_count":21,"thank_count":11,"votes":0,"author":"t2doo","score":200.189},{"id":378266,"title":"[三体迷] 来说一说欲罢不能的科幻小说吧","node":"scifi","create_at":1501122477,"clicks":8378,"reply_count":35,"favorite_count":52,"thank_count":0,"votes":0,"author":"zhongkouwei","score":200.033},{"id":377693,"title":"Python 为什么越来越火了？","node":"python","create_at":1500912675,"clicks":21007,"reply_count":92,"favorite_count":31,"thank_count":1,"votes":0,"author":"keisuu","score":199.953},{"id":375266,"title":"面试 PHP ，你们一般会问什么问题啊？","node":"qna","create_at":1500000132,"clicks":7554,"reply_count":28,"favorite_count":51,"thank_count":2,"votes":0,"author":"lianxiaoyi","score":199.93},{"id":374594,"title":"Windows 下安装 dig.exe 用于查询 DNS","node":"dns","create_at":1499771757,"clicks":13867,"reply_count":24,"favorite_count":47,"thank_count":5,"votes":0,"author":"Livid","score":199.537},{"id":376232,"title":"突然有一种想法。。“浪费水”究竟指的是什么？水龙头一直开着放水留进管道算是浪费么，但是这样水不一样在整个大环境中么？水费账单中也有“水循环处理过滤费”。这样来说是不是根本就不存在“浪费水”这种说法","node":"qna","create_at":1500373614,"clicks":17368,"reply_count":144,"favorite_count":15,"thank_count":0,"votes":0,"author":"Event","score":198.762},{"id":377882,"title":"创业公司，生产环境，按软件负载，买几十台二手服务器，可用性如何","node":"linux","create_at":1500975772,"clicks":13093,"reply_count":117,"favorite_count":22,"thank_count":1,"votes":0,"author":"a251922581","score":197.48},{"id":372731,"title":"V 在历史上还有那些惊艳奇葩或者清流？ 我先起个头。","node":"programmer","create_at":1499074384,"clicks":6812,"reply_count":37,"favorite_count":46,"thank_count":2,"votes":0,"author":"doggg","score":193.827},{"id":378551,"title":"移动亲自告诉你,dns 劫持,web 缓存,tcp 劫持,p2p 缓存都是怎么做到的.","node":"bb","create_at":1501210050,"clicks":7606,"reply_count":25,"favorite_count":43,"thank_count":2,"votes":3,"author":"KCheshireCat","score":178.937},{"id":377589,"title":"在 Docker 里面运行网易云音乐 （分享如何在 Docker 里运行 GUI 程序）","node":"create","create_at":1500883189,"clicks":9832,"reply_count":15,"favorite_count":41,"thank_count":5,"votes":0,"author":"raysonx","score":172.193},{"id":372452,"title":"迅雷是怎么做到开机启动的","node":"gts","create_at":1498965621,"clicks":7810,"reply_count":23,"favorite_count":41,"thank_count":1,"votes":0,"author":"KNOX","score":159.963},{"id":372351,"title":"Chrome 拓展管理 --- 二管家 --- 分组、自动管理、历史记录、更新通知 --- 开源免费","node":"create","create_at":1498898968,"clicks":6070,"reply_count":36,"favorite_count":41,"thank_count":4,"votes":0,"author":"AInoob","score":187.711},{"id":379269,"title":"分享自家千兆无线和万兆有线局域网拓扑","node":"create","create_at":1501485208,"clicks":10546,"reply_count":49,"favorite_count":40,"thank_count":3,"votes":1,"author":"trepwq","score":195.264},{"id":376810,"title":"尴尬，引导 U 盘是 FAT32，然而 Win10 最新 install.wim 超过 4G 了","node":"windows","create_at":1500556005,"clicks":29911,"reply_count":62,"favorite_count":40,"thank_count":0,"votes":0,"author":"springmarker","score":192.306},{"id":374156,"title":"Swift 入门资源推荐","node":"idev","create_at":1499627172,"clicks":5063,"reply_count":14,"favorite_count":36,"thank_count":2,"votes":1,"author":"xiqingongzi","score":142.53},{"id":372548,"title":"有限状态机的本质是不是也是 if-else，那这个概念的意义在于什么呢","node":"programmer","create_at":1499001903,"clicks":9548,"reply_count":41,"favorite_count":36,"thank_count":0,"votes":1,"author":"pythonee","score":160.164},{"id":377339,"title":"饥荒联机版(DST) 服务器容器 Docker","node":"create","create_at":1500788188,"clicks":8214,"reply_count":29,"favorite_count":35,"thank_count":2,"votes":0,"author":"Thoxvi","score":153.014},{"id":374719,"title":"有 V 友这几年成功转上海户口的吗？","node":"shanghai","create_at":1499829517,"clicks":11400,"reply_count":60,"favorite_count":35,"thank_count":2,"votes":0,"author":"alexanderchen","score":184.341},{"id":373543,"title":"你读过的对你影响最大的一本技术书是什么？","node":"survey","create_at":1499334798,"clicks":2606,"reply_count":84,"favorite_count":35,"thank_count":0,"votes":0,"author":"tttttttt","score":196.866},{"id":376340,"title":"Laravel 超大文件上传扩展，支持秒传","node":"php","create_at":1500431118,"clicks":7879,"reply_count":21,"favorite_count":34,"thank_count":3,"votes":1,"author":"peinhu","score":148.972},{"id":375648,"title":"分享一个刚刚整出来的 Python 版内网 tcp 穿透工具","node":"create","create_at":1500132840,"clicks":6664,"reply_count":6,"favorite_count":34,"thank_count":1,"votes":1,"author":"magensky","score":123.805},{"id":375363,"title":"各位 vim 大佬，在段尾编辑时，按 i 进入插入模式，怎么向右移动一格？","node":"vim","create_at":1500017456,"clicks":8336,"reply_count":47,"favorite_count":34,"thank_count":1,"votes":0,"author":"collo","score":163.028},{"id":374958,"title":"在 Markdown 中生成可视化图表","node":"create","create_at":1499909264,"clicks":8451,"reply_count":18,"favorite_count":34,"thank_count":3,"votes":1,"author":"Geeker","score":146.042},{"id":373852,"title":"Kotlin 入坑半年总结","node":"kotlin","create_at":1499445781,"clicks":54223,"reply_count":31,"favorite_count":34,"thank_count":3,"votes":3,"author":"sagaxu","score":164.901},{"id":372342,"title":"分享一个不错下载微软 Windows 和 office 官方 ISO 镜像的文件","node":"share","create_at":1498896101,"clicks":5953,"reply_count":19,"favorite_count":33,"thank_count":1,"votes":0,"author":"ajeef","score":131.692},{"id":378892,"title":"好像不少人不清楚 iTunes（ App Store） Gift Card 可以在官网买的？","node":"chamber","create_at":1501326784,"clicks":1387,"reply_count":45,"favorite_count":32,"thank_count":2,"votes":0,"author":"ETiV","score":158.236},{"id":378840,"title":"前后端分离的项目， API 接口如何防止重放攻击","node":"qna","create_at":1501312883,"clicks":20685,"reply_count":19,"favorite_count":32,"thank_count":0,"votes":0,"author":"lemayi","score":124.937},{"id":377942,"title":"断网了，好慌","node":"chamber","create_at":1500992645,"clicks":2726,"reply_count":44,"favorite_count":32,"thank_count":0,"votes":0,"author":"Wicheol","score":147.911},{"id":376143,"title":"《权力的游戏》回归了，用 Go 写了个 ZiMuZu 的 Alfred Workflow，方便追剧~~","node":"create","create_at":1500354928,"clicks":5398,"reply_count":19,"favorite_count":32,"thank_count":3,"votes":2,"author":"coa","score":142.594},{"id":373978,"title":"300 行 Java 代码实现区块链","node":"programmer","create_at":1499518063,"clicks":5802,"reply_count":10,"favorite_count":32,"thank_count":1,"votes":0,"author":"sunysen","score":119.666},{"id":373787,"title":"36 岁以上的程序员人家不要！","node":"career","create_at":1499420173,"clicks":11354,"reply_count":78,"favorite_count":32,"thank_count":0,"votes":0,"author":"andyL","score":183.337},{"id":373491,"title":"Flint OS VM - 在虚拟机里体验 Flint OS！","node":"share","create_at":1499326304,"clicks":9944,"reply_count":49,"favorite_count":32,"thank_count":1,"votes":2,"author":"carrieflint","score":163.205},{"id":372488,"title":"关于 SS 各种服务端 Python 、go、libev、R、更新到目前为止，你们的选择是？","node":"chamber","create_at":1498981618,"clicks":2930,"reply_count":47,"favorite_count":32,"thank_count":0,"votes":0,"author":"ajeef","score":150.983},{"id":378016,"title":"移动 HG8546M 极光猫超级管理员的账号密码","node":"bb","create_at":1501037245,"clicks":58323,"reply_count":11,"favorite_count":31,"thank_count":2,"votes":0,"author":"KCheshireCat","score":124.974},{"id":377145,"title":"你们的 telegram 群活跃么？","node":"qna","create_at":1500689565,"clicks":20571,"reply_count":35,"favorite_count":31,"thank_count":0,"votes":0,"author":"powtop","score":137.932},{"id":376805,"title":"编程学习应用 Growth 发布 3.0，在碎片时间里练习","node":"create","create_at":1500553578,"clicks":4315,"reply_count":18,"favorite_count":31,"thank_count":1,"votes":3,"author":"phodal","score":130.37},{"id":375477,"title":"多看 web 阅读器怎么实现的？查看 HTML 源码竟然看不到文本？","node":"qna","create_at":1500079959,"clicks":6045,"reply_count":15,"favorite_count":31,"thank_count":0,"votes":0,"author":"kingvieri","score":116.707},{"id":375467,"title":"明年虚岁 30 了，关于考研想听听大伙意见","node":"qna","create_at":1500054445,"clicks":8019,"reply_count":62,"favorite_count":31,"thank_count":0,"votes":0,"author":"irockytan","score":163.99},{"id":375297,"title":"分享一个自己的经历，通过免费的 WordPress 插件（公众号文章采集）「赚」到了四百多（其实算上人工是亏大了——！！！）","node":"create","create_at":1500003820,"clicks":8544,"reply_count":18,"favorite_count":31,"thank_count":1,"votes":0,"author":"AlwaysBee","score":125.053},{"id":372506,"title":"怎样“优雅的”使用两个手机？","node":"qna","create_at":1498987963,"clicks":14532,"reply_count":64,"favorite_count":31,"thank_count":0,"votes":0,"author":"JuicyJ","score":166.584},{"id":377646,"title":"分享下 U 盘安装 windows 10 1703 的折腾经历 （ NTFS U 盘的启动引导问题）","node":"share","create_at":1500891920,"clicks":14612,"reply_count":69,"favorite_count":30,"thank_count":1,"votes":1,"author":"lhx2008","score":175.59},{"id":377445,"title":"一位前端实习生的迷茫与困惑","node":"programmer","create_at":1500860845,"clicks":15444,"reply_count":38,"favorite_count":30,"thank_count":0,"votes":1,"author":"spiritree","score":139.645},{"id":378493,"title":"一个很赞的关于博弈论的游戏：信任如何建立","node":"share","create_at":1501178831,"clicks":6346,"reply_count":9,"favorite_count":26,"thank_count":6,"votes":1,"author":"xucheng","score":127.756},{"id":375699,"title":"提醒：请不要用各种百度网盘破解工具下载私人文件","node":"share","create_at":1500177918,"clicks":14155,"reply_count":61,"favorite_count":19,"thank_count":6,"votes":0,"author":"zqqian","score":157.558},{"id":375196,"title":"《我没有敌人》","node":"chamber","create_at":1499958235,"clicks":660,"reply_count":1,"favorite_count":1,"thank_count":5,"votes":0,"author":"tb4649120073rs","score":35.494},{"id":379389,"title":"关于之前的一件事情对社区的回应","node":"share","create_at":1501509916,"clicks":11070,"reply_count":16,"favorite_count":5,"thank_count":4,"votes":0,"author":"jellybool","score":60.312},{"id":379059,"title":"和自己女朋友/老婆什么都是反着来的，让我怀疑人生了","node":"libido","create_at":1501413869,"clicks":3881,"reply_count":109,"favorite_count":8,"thank_count":4,"votes":0,"author":"herozzm","score":161.264},{"id":376658,"title":"如果天空是黑暗的，那就摸黑生存；如果发出声音是危险的，那就保持沉默；如果自觉无力发光的，那就蜷伏于墙角。但不要习惯了黑暗就为黑暗辩护；不要为自己的苟且而得意；不要嘲讽那些比自己更勇敢热情的人们。我们可以卑微如尘土，不可扭曲如蛆虫。","node":"flamewar","create_at":1500526203,"clicks":2522,"reply_count":54,"favorite_count":5,"thank_count":4,"votes":9,"author":"DonaldTrump","score":114.833},{"id":378589,"title":"学习正则表达式的简单方法(中文翻译) https://github.com/cdoco/learn-regex-zh","node":"re","create_at":1501216950,"clicks":2853,"reply_count":0,"favorite_count":19,"thank_count":3,"votes":0,"author":"cdoco","score":79.956},{"id":378554,"title":"操你妈逼的","node":"chamber","create_at":1501210473,"clicks":1233,"reply_count":9,"favorite_count":0,"thank_count":3,"votes":0,"author":"yangff","score":31.118},{"id":378487,"title":"睡觉前突然胡思乱想。前端可以说是非常尴尬的一个工种了","node":"random","create_at":1501174496,"clicks":9128,"reply_count":69,"favorite_count":25,"thank_count":3,"votes":1,"author":"jin5354","score":170.119},{"id":378483,"title":"iView 一周年了，同时发布了 2.0 正式版，但这只是开始...","node":"js","create_at":1501172708,"clicks":7337,"reply_count":21,"favorite_count":22,"thank_count":3,"votes":0,"author":"Aresn","score":110.901},{"id":377561,"title":"给想要／已经 远程 工作的 xdjm 们提个醒 #远程# #劳动仲裁#","node":"career","create_at":1500879715,"clicks":3249,"reply_count":5,"favorite_count":1,"thank_count":3,"votes":1,"author":"run2","score":33.086},{"id":377233,"title":"V2EX 网友专享——UBNT 高端无线路由器 AmpliFi 团购活动！","node":"tuan","create_at":1500717474,"clicks":2861,"reply_count":38,"favorite_count":3,"thank_count":3,"votes":0,"author":"Ubiquiti","score":69.959},{"id":376942,"title":"摩拜月卡 5 元续费 3 个月了","node":"deals","create_at":1500608739,"clicks":12235,"reply_count":77,"favorite_count":1,"thank_count":3,"votes":0,"author":"c0mmand","score":104.412},{"id":376835,"title":"为 GitHub 提供论坛服务","node":"programmer","create_at":1500563451,"clicks":10741,"reply_count":64,"favorite_count":22,"thank_count":3,"votes":1,"author":"gitqlab","score":156.282},{"id":376222,"title":"函数名太长，做了一个查单词缩写的 Dictionary App 字典","node":"create","create_at":1500370594,"clicks":5587,"reply_count":38,"favorite_count":30,"thank_count":3,"votes":2,"author":"xzl380","score":155.628},{"id":376056,"title":"[视频]三星 Galaxy S8+只要 500 元？那些便宜的要死的北美合约机是怎么回事？","node":"create","create_at":1500336084,"clicks":7418,"reply_count":38,"favorite_count":18,"thank_count":3,"votes":0,"author":"andybest","score":115.912},{"id":375714,"title":"JavaScript 异步开发全攻略","node":"create","create_at":1500187580,"clicks":4601,"reply_count":10,"favorite_count":30,"thank_count":3,"votes":0,"author":"meathill","score":123.434},{"id":374218,"title":"PayPal $10 优惠券，限量 3000 张","node":"deals","create_at":1499657443,"clicks":3977,"reply_count":23,"favorite_count":6,"thank_count":3,"votes":0,"author":"jessynt","score":64.289},{"id":372821,"title":"Elvish：集强大表达力和友好界面为一身的 shell","node":"programmer","create_at":1499123466,"clicks":6786,"reply_count":18,"favorite_count":16,"thank_count":3,"votes":3,"author":"xiaq","score":95.823},{"id":372354,"title":"从暴力到 NAN 再到 NAPI——Node.js 原生模块开发方式变迁","node":"nodejs","create_at":1498899806,"clicks":4442,"reply_count":2,"favorite_count":15,"thank_count":3,"votes":2,"author":"XadillaX","score":74.399},{"id":379400,"title":"移动端免费用 Heroku“敏感词”","node":"programmer","create_at":1501513831,"clicks":1393,"reply_count":12,"favorite_count":16,"thank_count":2,"votes":0,"author":"wilsonwen","score":77.24},{"id":379396,"title":"老哥们斗图的表情包都哪里来的?","node":"internet","create_at":1501512193,"clicks":4474,"reply_count":17,"favorite_count":20,"thank_count":2,"votes":0,"author":"n7then","score":95.406},{"id":379282,"title":"分享一个注册美区小技巧","node":"apple","create_at":1501487209,"clicks":2888,"reply_count":2,"favorite_count":2,"thank_count":2,"votes":0,"author":"wessin","score":25.969},{"id":379231,"title":"即将步入大三的学长给 CS 专业新生的一些建议","node":"programmer","create_at":1501479577,"clicks":7542,"reply_count":47,"favorite_count":12,"thank_count":2,"votes":1,"author":"AlexLJ","score":103.928},{"id":378957,"title":"买了一罐 jd 自营的奶粉 遇到质量问题怎么办啊","node":"qna","create_at":1501379259,"clicks":5621,"reply_count":53,"favorite_count":3,"thank_count":2,"votes":0,"author":"kalsolio","score":80.634},{"id":378561,"title":"SSR 的作者被人肉了，但是我并不同情她","node":"shadowsocks","create_at":1501211767,"clicks":1303,"reply_count":23,"favorite_count":1,"thank_count":2,"votes":0,"author":"arakashic","score":43.173},{"id":378544,"title":"tensorflow CNN 卷积神经网络中的卷积层和池化层的代码和效果图","node":"python","create_at":1501209562,"clicks":2709,"reply_count":1,"favorite_count":7,"thank_count":2,"votes":1,"author":"fendouai_com","score":41.905},{"id":378210,"title":"samba 有没有易用的 webgui？","node":"linux","create_at":1501081988,"clicks":8966,"reply_count":13,"favorite_count":6,"thank_count":2,"votes":0,"author":"circsqua","score":50.101},{"id":377834,"title":"如何针对电信电视信号抓包测试组播 UDP 地址","node":"pointless","create_at":1500967753,"clicks":418,"reply_count":3,"favorite_count":11,"thank_count":2,"votes":0,"author":"linuxvivian","score":52.038},{"id":377660,"title":"闲得蛋疼于是实现了一个 iPhone SE 上的微信聊天样式","node":"create","create_at":1500896092,"clicks":4830,"reply_count":7,"favorite_count":7,"thank_count":2,"votes":0,"author":"geelaw","score":46.483},{"id":377473,"title":"Sophia：哲学知识共享社区（ Built by Vue）","node":"create","create_at":1500865650,"clicks":5255,"reply_count":36,"favorite_count":17,"thank_count":2,"votes":1,"author":"airingursb","score":107.567},{"id":377361,"title":"推荐一部剧 This Is Us","node":"tv","create_at":1500800028,"clicks":4763,"reply_count":13,"favorite_count":10,"thank_count":2,"votes":0,"author":"Yvette","score":61.469},{"id":377174,"title":"大家平时骑自行车一定要注意","node":"share","create_at":1500698483,"clicks":8650,"reply_count":78,"favorite_count":5,"thank_count":2,"votes":0,"author":"syahd","score":112.065},{"id":377093,"title":"[转] The Basic Law of Human Stupidity","node":"share","create_at":1500642000,"clicks":1057,"reply_count":1,"favorite_count":1,"thank_count":2,"votes":0,"author":"mdzz","score":20.964},{"id":377084,"title":"弄了个干净的极速版迅雷","node":"share","create_at":1500637042,"clicks":2796,"reply_count":2,"favorite_count":4,"thank_count":2,"votes":1,"author":"zmz125000","score":33.936},{"id":376838,"title":"今天，乌云关闭一周年","node":"chamber","create_at":1500564130,"clicks":1033,"reply_count":12,"favorite_count":0,"thank_count":2,"votes":0,"author":"voocel","score":28.941},{"id":376373,"title":"送出一些自家香椿酱，免费的。","node":"free","create_at":1500436718,"clicks":3265,"reply_count":116,"favorite_count":0,"thank_count":2,"votes":0,"author":"Sukizen","score":134.091},{"id":376118,"title":"分享 GITHUB 高级搜索功能","node":"share","create_at":1500347848,"clicks":2529,"reply_count":3,"favorite_count":4,"thank_count":2,"votes":0,"author":"xoxo419","score":32.836},{"id":376032,"title":"[网易内推] 2018 届校园招聘开始了！内推码 F70084R","node":"jobs","create_at":1500305266,"clicks":3724,"reply_count":4,"favorite_count":2,"thank_count":2,"votes":0,"author":"neteasexiaodong","score":28.223},{"id":375824,"title":"分享一个微信小程序，前端+后端","node":"wechat","create_at":1500255614,"clicks":13946,"reply_count":0,"favorite_count":2,"thank_count":2,"votes":1,"author":"vincenth520","score":27.543},{"id":375772,"title":"只是一个小工具，抛砖引玉吧","node":"python","create_at":1500216335,"clicks":3243,"reply_count":6,"favorite_count":1,"thank_count":2,"votes":1,"author":"intohole","score":29.085},{"id":375437,"title":"发几张自己养的蚂蚁的照片","node":"pet","create_at":1500041709,"clicks":6429,"reply_count":32,"favorite_count":2,"thank_count":2,"votes":0,"author":"ech0x","score":56.769},{"id":375264,"title":"UNIX 时间戳超过 1500000000 啦","node":"share","create_at":1500000002,"clicks":4163,"reply_count":12,"favorite_count":2,"thank_count":2,"votes":3,"author":"orzfly","score":42.334},{"id":374901,"title":"分享一个用 Python 获取 V2 首页文章的爬虫","node":"programmer","create_at":1499869210,"clicks":4681,"reply_count":32,"favorite_count":13,"thank_count":2,"votes":0,"author":"PythoneerDev6","score":89.451},{"id":374879,"title":"写了一个帮助找公寓的工具（寓住 - 根据城市筛选公寓）来这儿分享下…希望能得到点看法和意见之类的","node":"create","create_at":1499864372,"clicks":3282,"reply_count":11,"favorite_count":13,"thank_count":2,"votes":1,"author":"agoodob","score":70.097},{"id":379262,"title":"“每日签到”用英文怎么说？","node":"programmer","create_at":1501484538,"clicks":59972,"reply_count":77,"favorite_count":9,"thank_count":0,"votes":3,"author":"Reign","score":121.002},{"id":374733,"title":"支付宝免费领取国际驾照（ 9.9 邮费），听说不靠谱？","node":"qna","create_at":1499830766,"clicks":55166,"reply_count":99,"favorite_count":16,"thank_count":0,"votes":1,"author":"wildcat007","score":159.918},{"id":378653,"title":"现在网上的美国信用卡生成器都失效了么","node":"programmer","create_at":1501229225,"clicks":54245,"reply_count":60,"favorite_count":9,"thank_count":0,"votes":0,"author":"redapple0204","score":97.901},{"id":377604,"title":"电信已停卡 1 年多的号码欠费 6 百，不能销卡，必须缴费？？？","node":"qna","create_at":1500885812,"clicks":48221,"reply_count":74,"favorite_count":8,"thank_count":0,"votes":0,"author":"hhhxk","score":108.784},{"id":377249,"title":"PHP curl 无法使用非 80 端口的代理？","node":"php","create_at":1500725189,"clicks":46054,"reply_count":11,"favorite_count":0,"thank_count":0,"votes":0,"author":"nmdx","score":21.738},{"id":375270,"title":"记一次 12315.cn 投诉京东的过程","node":"internet","create_at":1500000441,"clicks":44276,"reply_count":22,"favorite_count":13,"thank_count":0,"votes":0,"author":"SoraneKazehana","score":71.698},{"id":372845,"title":"京东小白信用的上限是多少？为什么能达到 100 分以上？","node":"qna","create_at":1499133375,"clicks":43120,"reply_count":9,"favorite_count":0,"thank_count":0,"votes":0,"author":"beingbin","score":19.672},{"id":373866,"title":"一加 5 和 小米 6 ？ choose what？","node":"android","create_at":1499469993,"clicks":40287,"reply_count":72,"favorite_count":2,"thank_count":0,"votes":0,"author":"lamls","score":88.604},{"id":376718,"title":"今天上海的平安科技给了 offer，但除了在平安上班，其他的东西都是和外包公司签的，有什么影响吗？","node":"career","create_at":1500537304,"clicks":37330,"reply_count":30,"favorite_count":3,"thank_count":0,"votes":0,"author":"Pool","score":49.528},{"id":377990,"title":"新人刚入职如何看懂公司项目代码","node":"android","create_at":1501033177,"clicks":36116,"reply_count":64,"favorite_count":26,"thank_count":0,"votes":0,"author":"neimengwuyanzu","score":152.495},{"id":375950,"title":"人生第一次得急性肠胃炎，已经第五天了，还没好....","node":"fit","create_at":1500283321,"clicks":35546,"reply_count":98,"favorite_count":18,"thank_count":0,"votes":0,"author":"ajeef","score":162.479},{"id":372983,"title":"今天面试被人评价了个城府太深","node":"career","create_at":1499157298,"clicks":35138,"reply_count":78,"favorite_count":17,"thank_count":1,"votes":1,"author":"kslr","score":146.467},{"id":379145,"title":"实打实的项目 1k+star github 项目 为啥我没有面试机会","node":"android","create_at":1501465043,"clicks":34987,"reply_count":122,"favorite_count":14,"thank_count":0,"votes":0,"author":"MagicMashRoom","score":174.463},{"id":373187,"title":"分享一下顶配 MacBook 2017 使用一周后的感受","node":"apple","create_at":1499230368,"clicks":33968,"reply_count":57,"favorite_count":8,"thank_count":0,"votes":0,"author":"oulongqi","score":91.433},{"id":372801,"title":"上海如家、七天等经济型酒店长租三个月","node":"shanghai","create_at":1499095993,"clicks":33257,"reply_count":47,"favorite_count":11,"thank_count":0,"votes":0,"author":"wqlin","score":90.412},{"id":379227,"title":"工信部投诉移动公司，不给公网 ip 地址。\n10086 来电同意退款。","node":"bb","create_at":1501478254,"clicks":33138,"reply_count":103,"favorite_count":8,"thank_count":0,"votes":5,"author":"katios","score":147.408},{"id":376260,"title":"小米 6 值得当主力机吗？","node":"android","create_at":1500383236,"clicks":32383,"reply_count":124,"favorite_count":7,"thank_count":0,"votes":0,"author":"lamls","score":155.385},{"id":374545,"title":"Xshell5 可以查看已经保存的密码吗？","node":"qna","create_at":1499761006,"clicks":32239,"reply_count":10,"favorite_count":6,"thank_count":0,"votes":1,"author":"qcloud","score":40.381},{"id":379344,"title":"为什么顺丰拒收退回还要收取寄件人回程运费，而其他大部分快递拒收退回都不收回程运费的？","node":"qna","create_at":1501498216,"clicks":32061,"reply_count":2,"favorite_count":0,"thank_count":0,"votes":0,"author":"qui9090","score":12.375},{"id":377403,"title":"莫斯利安，安慕希这类常温酸奶是不是不算真正的酸奶？","node":"qna","create_at":1500818557,"clicks":31660,"reply_count":26,"favorite_count":6,"thank_count":0,"votes":0,"author":"qui9090","score":54.363},{"id":378922,"title":"蓝牙鼠标真的比 2.4G 响应慢很多吗？","node":"programmer","create_at":1501338134,"clicks":31556,"reply_count":60,"favorite_count":4,"thank_count":0,"votes":0,"author":"pulelt","score":82.36},{"id":373168,"title":"感觉这代 835 的机器好给力","node":"android","create_at":1499225394,"clicks":31541,"reply_count":117,"favorite_count":7,"thank_count":0,"votes":0,"author":"cyberdaemon","score":148.359},{"id":379004,"title":"一年不知安卓流畅为何物","node":"android","create_at":1501392259,"clicks":31172,"reply_count":169,"favorite_count":5,"thank_count":0,"votes":0,"author":"FanWall","score":194.347},{"id":374796,"title":"请教一下在海外使用大陆 ip 的方式","node":"bb","create_at":1499842742,"clicks":30304,"reply_count":40,"favorite_count":23,"thank_count":0,"votes":0,"author":"elikoi17","score":119.319},{"id":374629,"title":"给大家讲个事，我在入职前被华为单方面解约了","node":"career","create_at":1499782953,"clicks":30270,"reply_count":129,"favorite_count":15,"thank_count":0,"votes":0,"author":"chiyahoho","score":184.318},{"id":373537,"title":"graphql 有未来吗?","node":"programmer","create_at":1499333017,"clicks":30007,"reply_count":17,"favorite_count":8,"thank_count":0,"votes":1,"author":"caniuse","score":53.309},{"id":372282,"title":"上海电信新乐享家 199 元套餐直接 500M 宽带搭配 4G+40G 本地融合流量无敌了","node":"bb","create_at":1498867170,"clicks":29758,"reply_count":66,"favorite_count":12,"thank_count":0,"votes":0,"author":"wsgzao","score":112.301},{"id":375578,"title":"一根网线分成两根会不会有影响？","node":"qna","create_at":1500112094,"clicks":29756,"reply_count":60,"favorite_count":11,"thank_count":0,"votes":0,"author":"GeekCat","score":103.301},{"id":376819,"title":"Mac 上最好用的 NTFS 读写 App 是哪个？","node":"macos","create_at":1500559689,"clicks":29712,"reply_count":39,"favorite_count":15,"thank_count":1,"votes":0,"author":"ichanne","score":99.299},{"id":373703,"title":"夏天来了，共享单车变成了共享铁板烧","node":"life","create_at":1499405069,"clicks":29532,"reply_count":24,"favorite_count":0,"thank_count":0,"votes":0,"author":"noe132","score":34.293},{"id":373737,"title":"laravel 5.5 什么时候发布，我已经等得饥渴难耐了","node":"programmer","create_at":1499411812,"clicks":28201,"reply_count":8,"favorite_count":0,"thank_count":0,"votes":0,"author":"caniuse","score":18.247},{"id":378763,"title":"Google Cloud Platform 支持什么样的信用卡呢？","node":"qna","create_at":1501288868,"clicks":27710,"reply_count":21,"favorite_count":6,"thank_count":0,"votes":0,"author":"permaylau","score":49.23},{"id":374043,"title":"微信二维码收到款都不知道是谁付的，有办法知道吗？微信这么做是脑残还是有什么顾虑？","node":"qna","create_at":1499568453,"clicks":27617,"reply_count":23,"favorite_count":2,"thank_count":0,"votes":0,"author":"doubleflower","score":39.226},{"id":378334,"title":"发现安卓剪贴板被人强奸了","node":"android","create_at":1501134062,"clicks":27179,"reply_count":20,"favorite_count":7,"thank_count":0,"votes":1,"author":"commonhub","score":53.21},{"id":372706,"title":"乐视是不是药丸：贾跃亭夫妇及乐视系三家公司 12 亿存款被冻结","node":"share","create_at":1499069741,"clicks":27079,"reply_count":13,"favorite_count":2,"thank_count":0,"votes":0,"author":"yongshou","score":29.207},{"id":375549,"title":"阿里面试，视频面试 与会人是 hr 和 leader，是第几面呢？","node":"cv","create_at":1500103648,"clicks":26857,"reply_count":34,"favorite_count":2,"thank_count":0,"votes":0,"author":"biglee0304","score":50.198},{"id":378299,"title":"大家的 NAS 都用什么系统啊","node":"nas","create_at":1501126811,"clicks":25985,"reply_count":14,"favorite_count":13,"thank_count":0,"votes":0,"author":"m939594960","score":63.165},{"id":378616,"title":"iOS 信任证书有什么风险吗？","node":"ios","create_at":1501224561,"clicks":25815,"reply_count":19,"favorite_count":0,"thank_count":0,"votes":0,"author":"RandomUser","score":29.159},{"id":374410,"title":"中国联通异地无法换套餐？","node":"life","create_at":1499735075,"clicks":25688,"reply_count":30,"favorite_count":0,"thank_count":0,"votes":0,"author":"didikee","score":40.154},{"id":374516,"title":"Resilio Sync 是被墙了么= =用检查的说被墙了,程序也不正常了","node":"share","create_at":1499755720,"clicks":25572,"reply_count":23,"favorite_count":7,"thank_count":0,"votes":0,"author":"huixia0010","score":54.149},{"id":374068,"title":"简单评价 Sony DPT-RP1 - 13.3″ 电子墨水屏 PDF 阅读器","node":"sony","create_at":1499579529,"clicks":25462,"reply_count":55,"favorite_count":21,"thank_count":0,"votes":3,"author":"ynyounuo","score":134.145},{"id":375697,"title":"美区 Apple ID 能绑定国内信用卡或储蓄卡吗？","node":"apple","create_at":1500177813,"clicks":25450,"reply_count":21,"favorite_count":7,"thank_count":0,"votes":0,"author":"panamera","score":52.145},{"id":377672,"title":"Android 版微信朋友圈上传图片压缩的问题","node":"android","create_at":1500904697,"clicks":25289,"reply_count":30,"favorite_count":5,"thank_count":0,"votes":0,"author":"wangwang24","score":55.138},{"id":378331,"title":"老铁们，遇到一个 Chrome 的 ERR_ADDRESS_UNREACHABLE 问题，求助","node":"macos","create_at":1501133556,"clicks":25210,"reply_count":10,"favorite_count":1,"thank_count":0,"votes":0,"author":"Expl4it","score":23.135},{"id":375117,"title":"听说是月经，到 2018 年春节止，有哪些价格相对亲民的 Android 机型，拥有接近亲儿子的体验？","node":"android","create_at":1499938594,"clicks":25092,"reply_count":104,"favorite_count":11,"thank_count":1,"votes":2,"author":"gam2046","score":156.13},{"id":373374,"title":"国内和国外视频聊天，用什么软件比较好?","node":"qna","create_at":1499302444,"clicks":24700,"reply_count":70,"favorite_count":1,"thank_count":0,"votes":0,"author":"jadetang","score":83.115},{"id":378183,"title":"求助 S8 国行 play 商店一直显示未认证,网页版 play 上看不到这个设备,查找我的设备也找不到","node":"android","create_at":1501073467,"clicks":24614,"reply_count":20,"favorite_count":0,"thank_count":0,"votes":0,"author":"yangyaofei","score":30.111},{"id":377637,"title":"安卓上什么浏览器干净好用无广告？","node":"programmer","create_at":1500890252,"clicks":24569,"reply_count":112,"favorite_count":16,"thank_count":0,"votes":0,"author":"Technetiumer","score":170.109},{"id":374530,"title":"外部应用跳到微信内任意网页，这个如何做到的","node":"share","create_at":1499758748,"clicks":23781,"reply_count":63,"favorite_count":12,"thank_count":0,"votes":0,"author":"yudun1989","score":109.077},{"id":376962,"title":"长期不用的微博账号会被盗？？？","node":"gts","create_at":1500612494,"clicks":23715,"reply_count":92,"favorite_count":4,"thank_count":0,"votes":0,"author":"scriptB0y","score":114.074},{"id":377512,"title":"问一下 三星手机的 knox(安全文件夹)好用吗","node":"android","create_at":1500871388,"clicks":23598,"reply_count":14,"favorite_count":0,"thank_count":0,"votes":0,"author":"magiclu","score":24.069},{"id":374009,"title":"时隔这么多年， Linux 桌面应用依然是坑","node":"linux","create_at":1499531477,"clicks":23466,"reply_count":154,"favorite_count":11,"thank_count":0,"votes":0,"author":"ecloud","score":197.063},{"id":377227,"title":"电视上看油管的正确姿势是什么？","node":"qna","create_at":1500715386,"clicks":23261,"reply_count":24,"favorite_count":6,"thank_count":0,"votes":0,"author":"zhaibin18","score":52.055},{"id":374480,"title":"马云无人超市识别购买物品的原理是什么？谁来说说？","node":"qna","create_at":1499747835,"clicks":22882,"reply_count":95,"favorite_count":24,"thank_count":1,"votes":0,"author":"gdtv","score":182.038},{"id":378048,"title":"nvidia shield TV 感觉挺好用的","node":"share","create_at":1501042617,"clicks":22860,"reply_count":37,"favorite_count":18,"thank_count":1,"votes":0,"author":"vitalbo","score":106.037},{"id":379182,"title":"被阿里挂了两次的简历求指点","node":"cv","create_at":1501470283,"clicks":22606,"reply_count":112,"favorite_count":18,"thank_count":1,"votes":0,"author":"hzw758","score":181.026},{"id":375317,"title":"老铁们有啥隔音神器可以推荐下帮助睡眠吗？","node":"qna","create_at":1500008478,"clicks":22568,"reply_count":42,"favorite_count":10,"thank_count":0,"votes":0,"author":"hanzichi","score":82.024},{"id":376028,"title":"K2P 这种路由器到底千兆到哪儿去了","node":"router","create_at":1500304367,"clicks":22527,"reply_count":15,"favorite_count":0,"thank_count":0,"votes":0,"author":"twoyuan","score":25.023},{"id":377311,"title":"额...苹果现在已经不给换整机了么... 现在感觉整个一组装 iPhone","node":"iphone","create_at":1500778014,"clicks":22416,"reply_count":75,"favorite_count":2,"thank_count":0,"votes":0,"author":"byuan04","score":91.018},{"id":378985,"title":"京东的电子发票太恶心了吧,这可怎么报销啊!","node":"gts","create_at":1501387013,"clicks":21915,"reply_count":91,"favorite_count":1,"thank_count":0,"votes":0,"author":"dream7758522","score":103.995},{"id":376070,"title":"是“已作修改”还是“已做修改”？","node":"qna","create_at":1500341297,"clicks":21312,"reply_count":65,"favorite_count":4,"thank_count":0,"votes":0,"author":"FollowHeart","score":86.967},{"id":374772,"title":"[直播贴] 还在北京奔波？跟币信一起回长沙吧！","node":"jobs","create_at":1499838290,"clicks":21225,"reply_count":135,"favorite_count":11,"thank_count":0,"votes":0,"author":"rayston92","score":177.963},{"id":377362,"title":"谁知道 iCloud 中 Textlnput 这个文件是什么啊？删掉了还会出现","node":"apple","create_at":1500800075,"clicks":21215,"reply_count":5,"favorite_count":0,"thank_count":0,"votes":0,"author":"mrhmlin","score":14.963}],"post_rankings":{"score":[379097,377051,376495,376057,378748,378730,379088,372880,373901,379031,377223,379172,378173,379103,377158,378248,376443,372462,377939,377060,377944,375275,379047,375186,373158,376710,374908,378841,372893,376651,376024,374721,374824,375658,374418,378822,372829,376899,376429,372550,378165,374395,374778,374067,374056,375011,373389,377413,377725,378264,378500,372589,377712,374638,374258,378239,378509,372961,379407,378511,378811,377734,377861,374344,376351,377449,375610,379176,372924,376061,374201,372657,377419,374826,375151,373635,378113,376138,378142,374364,376825,375934,377321,378546,376335,375831,376552,373222,375007,376960,373781,375329,378645,376894,378266,377693,375266,374594,376232,377882],"favorite_count":[379097,378730,378748,376495,376057,377223,372880,378173,379103,379088,377944,374908,375186,376651,377939,376710,373158,379047,378248,376024,376429,372589,372550,374778,378500,377060,376443,372961,375658,373901,374056,377321,374721,372462,377449,377413,377051,378266,375275,375266,378264,373781,378511,374594,372829,378165,377712,376335,372731,378645,374364,378551,378509,376899,374067,377589,372452,372351,379269,378822,376810,377861,374824,372893,374418,374258,374156,372548,378811,377339,376552,374719,373543,376340,375648,375363,374958,373852,372342,378892,378841,378840,377942,376143,373978,373787,373491,372488,378016,377693,377145,376805,375477,375467,375297,372506,379176,377734,377646,377445],"thank_count":[379172,379097,376057,379088,379047,374418,376894,378546,372829,378841,377223,374721,376899,378173,376710,378493,377944,377051,376825,375699,375275,377589,376495,375658,375196,374594,379389,379059,378730,377939,377712,376658,373901,372961,372351,379269,378589,378554,378487,378483,377561,377413,377321,377233,377060,376942,376835,376340,376222,376143,376056,375714,375186,374958,374778,374218,373852,372880,372821,372550,372354,379407,379400,379396,379282,379231,379103,378957,378892,378748,378561,378551,378544,378509,378500,378210,378165,378016,377834,377660,377473,377449,377361,377339,377174,377093,377084,376838,376373,376118,376032,375824,375772,375437,375266,375264,374901,374879,374719,374156],"clicks":[379103,379262,378016,374733,378653,373852,372462,377051,377604,373222,377249,375270,372845,377060,373866,374395,376718,376651,376960,378822,377990,377158,375950,372983,379145,373901,373187,376429,372801,379227,378248,376260,374545,376495,379344,377403,378922,373168,376443,379004,374796,374629,373537,376810,372282,375578,376819,373703,378165,378811,378841,376351,373737,378763,374043,378334,372706,375549,379088,373389,377419,378299,378616,374410,374516,374068,375697,377672,378331,375117,373374,378183,377637,379047,374530,376962,377512,379407,378142,374009,377227,377734,374480,378048,379182,375317,379176,374201,376028,377311,375831,372893,372880,378985,374258,374344,372961,376070,374772,377362]},"comments":[{"id":4492746,"topic_id":372983,"commenter":"F281M6Dh8DXpD1g2","thank_count":112,"no":2,"topic_title":"今天面试被人评价了个城府太深","content":"你这算啥，我有次去面试对面说我太胖.......","create_at":1499157571},{"id":4506695,"topic_id":373901,"commenter":"eyp82","thank_count":83,"no":2,"topic_title":"入职一周 写点体会 拉点仇恨 有图有真相","content":"哥们最后一张... 有这么粗?","create_at":1499485563},{"id":4531661,"topic_id":375610,"commenter":"matsuijurina","thank_count":68,"no":6,"topic_title":"罗永浩 Big Bang 被指抄袭效仿 Pin","content":"pin 的作者有一个实锤，那就是锤子的产品经理向他询问了 pin 的分词功能实现细节。话说中国的独立开发者真的是很 nice，只要自己能力所及，被问到 app 的核心实现细节都是倾囊相授，根本没有什么商业敏感性。记得 vvebo 的作者被问到为什么 app 相比竞品滑动这么流畅时，直接写了一篇长文阐明了 vvebo 的缓存和渲染原理，可以说是毫无保留。对比我认识的一些老印开发，他知道 100 分的东西，最多告诉你 5 分。对于这些 nice 的中国独立开发者，商业公司真的应该多给些尊重。现在有些极端锤粉在 pin 作者微博里攻击说 pin 的分词核心技术也不是自己开发的，这就像有个公司抄袭了锤子的系统后攻击说 android 也不是锤子自己开发的，实在让人无语。","create_at":1500122629},{"id":4523773,"topic_id":375007,"commenter":"processzzp","thank_count":62,"no":15,"topic_title":"中国区 Apple ID 的 iCloud 将迁到贵州数据中心，大家怎么看？","content":"@dodo20120\n过去十多个月来，每当我在全球各地讨论这个议题的时候，每次总是有人会这样对我说：“我并不担心隐私被侵犯因为我没什么不可告人之处” 我也对他们回应相同的答复。我拿了一支笔，写下自己的电子邮件，然后说：“这上面是我的电子邮件，我希望当你回到家之后，把你自己所有的电邮帐号和密码都寄给我。不是只提供你工作上使用那个正本经的电子邮件，而是全部的电邮。这样我可以在线上用你的帐号来了解你的一举一动，然后把我认为有趣的事物公开出来。不管怎样，如果你不是个坏人，如果你没做过坏事，你应该没没什么不可告人之处。“然而从来没有一个人回应我这项提议。\nGlenn Greenwald 为何隐私重要 - TED 演讲","create_at":1499923658},{"id":4535586,"topic_id":375871,"commenter":"guoer","thank_count":60,"no":1,"topic_title":"早上开会喊口号真的有必要吗....","content":"离职","create_at":1500264041},{"id":4584234,"topic_id":379088,"commenter":"1ychee","thank_count":51,"no":16,"topic_title":"\"同类软件的鼻祖” Seer 抄走了我的 GPL 代码去卖钱……","content":"@xupefei 我们网店出售 Seer，如果属实，我们会下架 Seer，除非开发商能够和您达成一定的协议。\n商品链接： https://www.lizhi.io/product/seer","create_at":1501429986},{"id":4544666,"topic_id":376507,"commenter":"akwIX","thank_count":50,"no":1,"topic_title":"若那艰难的日子真来了，你们还敢用国外的服务吗？","content":"安心吃猪饲料吧","create_at":1500467737},{"id":4573226,"topic_id":378264,"commenter":"66beta","thank_count":49,"no":19,"topic_title":"感觉自己好穷。。。只能努力工作","content":"35 岁 你因为身体越来越差\n加班越来越少\n晋升的速度也越来越缓慢\n那天下班，媳妇告诉你\n孩子要上幼儿园了\n双语的一个月 3000\n你皱了皱眉头，那边就已经不耐烦了\n“四单元的老王家孩子，一个月 6000 ”\n“你已经这样了，你想让孩子也输？”\n你没说话，回屋给媳妇转了 6000 块钱\n这笔钱，你原本打算给自己过个生日，买个新电脑\n38 岁，孩子上了一年级\n老师说一年级最关键，打好基础很重要\n你笑着说，是是是，老师您多照顾\n新生接待的老师看着你不明事理的脸\n给你指了一条明路\n“课外辅导班，一个月 2200 ”\n40 岁的时候，孩子上了三年级\n老师说，三年级，最关键，承上启下很重要\n你笑着说：是是是，正打算再报个补习班\n44 岁，孩子上了初中\n有一天回到家，她对你说\n爸爸，我想学钢琴\n你没什么犹豫的\n你以为这些年，你已经习惯了\n但那句“爸爸现在买不起”你始终说不出口\n好在孩子比较懂事\n她说：爸爸没事，要不我先学陶笛也可以\n你看着这么懂事的孩子，却开心不起来\n46 岁，孩子上了一个不好不差的高中\n有一天你在开会，接到了老师的电话\n电话里说你的孩子在学校打架了\n叫你去一趟\n你唯唯诺诺的\n和那个比你还小 5 岁的领导请了个假\n到学校又被老师训了一通\n无非台词就是那一句\n你们做家长的就知道工作，能不能陪陪孩子\n你看着这个老师，有点可笑\n好像当时说：\n家长在外辛苦点\n多赚点钱让孩子多补补课的和他不是一个人\n50 岁，孩子上了大学\n很争气，是一个一本\n他学的专业你有点看不懂\n你只知道工作不一定好找\n而且学费还死贵\n你和他深夜想聊聊\n准备了半斤白酒，一碟花生米\n你说着那些曾经你最讨厌的话\n还是要为以后工作着想\n挑个热门的专业\n活着比热爱重要\n你们从交流变成了争吵\n你发现，你老了\n老到可能都打不过这个 18 岁的孩子\n你说不过他，只能说一句：我是你爸爸！\n孩子看着你，知道再怎么争辩都没用\n这场确立你最后威严的酒局不欢而散\n你听的不真切\n在孩子回自己屋的路上好像叨叨了一句\n“我不想活的像你一样”\n怎么就哭了呢？ 50 岁的人了\n一定是酒太辣了，对不对\n一定是酒太辣了\n55 岁，孩子工作了，似乎有一点理解你了\n但你却反了过来，你说不要妥协\n56 岁，孩子也结婚了\n你问他喜欢那个姑娘么\n他愣了愣说：喜欢吧\n60 岁，辛苦了一辈子，想出去走走\n身边的那个人过了 30 年\n你依旧分不清到底喜不喜欢\n你们开始规划旅游路线\n这么多年了\n你们还是存在分歧，还是在争吵\n某个瞬间，你觉得\n这样可能也挺好\n一切都准备好了\n儿子说：爸妈，我工作太忙了\n可以帮我照顾一下孩子么\n你们退了机票，又回到了 30 年前\n70 岁，孩子的孩子也长大了，不用天天操心了 你下定决心说：一定要去玩一趟 可是手边的拐杖 只能支持你走到楼下的花园 75 岁，你在医院的病床上 身边聚满了人，你迷迷糊糊的看见医生摇了摇头 周围那些人神情肃穆 你明白了，你要死掉了 你没有感到一丝害怕 你突然问自己，我到底是什么时候死掉的呢？ 你想起来 30 岁的那场婚礼 原来，那时候，你就死掉了吧 依照惯例 死前的 3 秒，你的大脑要走马灯 倒叙你这 75 个年头的一生 画面一张一张的过 1 秒 2 秒 两秒过去了 你面无表情的看着这两秒内的回忆 第 3 秒 突然你笑了 原来已经回到了 15 岁的那一年 你看见一个男孩 他叼着一袋牛奶，背着书包 从另一个女孩家的阳台下跑过 那个男孩朝窗户里看了看 那是 15 岁的你暗恋的那个女孩子 你想不起来她长什么样子了 最后一秒你努力的回忆着 然后终于笑了出来 3 秒过去了 身边的人突然间开始嚎啕大哭 你可能听不清了 你最后听到的嘈杂的声音 是一群十五六的少年 起着哄说的 答应他 答应他 答应他","create_at":1501138955},{"id":4532223,"topic_id":375610,"commenter":"matsuijurina","thank_count":49,"no":46,"topic_title":"罗永浩 Big Bang 被指抄袭效仿 Pin","content":"朱萧木的回应出来，才让我真正失去了对锤子团队的尊重。学术界的一句老话：Publish or perish. 你内部创意更早又怎样？说不定 pin 作者翻出来他 2010 年的日记证明他的创意还早一些。再说不定诺基亚那个什么都研究一下的研究院十几年前就把现在智能手机上所有的主流功能都内部讨论过一番了。你内部有 idea，但别人的论文或产品先出来了，你怎么办，你只能憋着，要么放弃这个 idea，要么做个有点不一样的，但做文献综述的时候提及或感谢先行者，这是体面的做法。当然，做 app 这一块没有学术界那么严格的规范，都是你抄我我抄你，但是锤子不是一家最喜欢讲究体面的公司吗？这件事情上最不体面的就是锤子的产品经理找到 pin 开发者询问了分词技术实现细节。至于这个实现细节到底复不复杂，甚至锤子之后有没有从 pin 开发者的回答中得到帮助，这都不是重点。重点是你跑去问了，这就意味着两点：1，你知道有竞品或先行者存在。2，你主观希望从先行者那里得到某些帮助。在学术界，如果第 1 点你不满足，结果只是退稿，原因是你没有充分进行文献调研，对前人研究了解不够。但如果你两点都满足，还发了文章，并且对先前你咨询过的研究团队只字不提，你等着看看那个团队会不会愤怒地来怼你。跟学术圈不同的是，在这件事情上界定锤子抄袭非常困难，锤子有一百种方法证明自己没有抄袭，但这是这件事情的重点吗？根本不是。请仔细想想，为什么 pin 的作者会那么愤怒？之前说过，中国的独立开发者普遍都很 nice， 很善良，但他们都不傻。如果当时来找开发者咨询的不是锤子的产品经理，而是别的某家抄袭成性臭名昭著的公司的员工，我想他是绝对不会得到热情的答复的。这位开发者在答复锤子的产品经理时，默认锤子是一家体面的公司，这样的评价是鉴于锤子积极捐助支持开源社区，体现过对开发者群体的尊重，那么开发者自然也会尊重这家公司。即使它来询问某些技术问题，也不会怀着高倍的戒心来回答。但之后锤子的所作所为，显然让这位开发者失望了。其实大爆炸第一次在发布会出来，很快就有用户说这个和 pin 的某个功能有点像。锤子的解释是没有任何关系，创意是锤子自己想出来的。之后大家就都不在意了，本来在 5 寸见方的屏幕上也玩不出多少花来，业界生态一直也是抄来改去，有点像也就那么回事吧，说不定是碰巧呢，况且 pin 的开发者也没特别说什么。如果不是这次这位开发者忍无可忍爆出私信截图，可能没有人会想到锤子不仅知道 pin 的分词功能存在，还主动找上门询问过产品核心细节。 这可完全不像朱萧木所谓的“坦坦荡荡”。真的坦荡，就应该在大爆炸刚发布被问到和 pin 相似时，主动承认之前向 pin 开发者求教过，表示对 pin 开发者的感谢，然后再列出从创意到产品实现环节的一二三四五，证明自己从主观意图和客观事实上确实没有抄袭。如果锤子这么做了，pin 的开发者还会炸毛吗？但锤子没有，那么它就离自己所标榜的体面或者理想主义相去甚远了。直到朱萧木这篇充满傲慢和无辜感的澄清信，结尾时最后的那个“ X ”，言下之意大概是“怎么碰上了 pin 开发者这么一个想靠黑锤子蹭热度的 sb ”，可能是我过度解读了，但至少不会是“对不起，谢谢你”这样的语气吧。我对锤子团队最后的一点尊重已经没有了。","create_at":1500137063},{"id":4553094,"topic_id":377051,"commenter":"rust","thank_count":48,"no":90,"topic_title":"关于 UCloud 赖账的 10 万 推广费，想请大家评评理","content":"哈哈哈哈哈哈哈哈哈哈哈哈哈哈哈哈哈哈哈哈哈哈哈哈哈哈哈哈哈哈哈哈哈哈哈哈哈哈哈哈哈哈哈哈哈哈哈哈哈哈哈哈哈哈哈哈哈哈哈哈哈哈哈哈哈哈哈哈哈哈哈哈哈哈哈哈哈哈哈哈哈哈哈哈哈哈哈哈哈哈哈哈哈哈哈哈哈哈哈哈哈哈哈哈哈哈哈哈哈哈哈哈哈哈哈哈哈哈哈哈\n我发这么多\"哈\"字并不是灌水,是真的开心.今天早上的会议上,我司决定要在 8 月份新上线的项目上使用 UCloud 的服务.年度预算 180W.然后我把这个页面发给 BOSS 看了,BOSS 给我发了一个大红包,让我重新评估云服务厂商...","create_at":1500638077},{"id":4513949,"topic_id":374344,"commenter":"matsuijurina","thank_count":47,"no":29,"topic_title":"严肃问个问题，为什么年轻程序员中，喜好二次元文化的比例这么高？ 百思不得其解…","content":"你看到的只是表面现象。实际情况是，除了程序员行业以外，哪个行业的年轻人敢站出来明目张胆地说自己喜欢二次元。公务员敢吗? 教师敢吗？ 国企员工敢吗？ 银行金融从业者敢吗？只要在朋友圈里发一条去逛漫展的信息，分分钟就会被同事视为异类，幼稚，不上进，职业生涯都会受影响。要是什么女装大佬之类的估计直接会被扭送精神病院了。其实不是程序员里女装大佬多，而是女装大佬想要获得和其他人相同的社会经济地位和体面的职业，只有拼命磨炼技艺，成为独当一面的程序员这华山一条路可走。异装，cos，偶像宅...这些都是某种亚文化符号，它们既然会受到一些年轻人喜爱，那就说明它们肯定满足了年轻人的某些精神需求。而年轻人的精神需求，在这个国度，在某个春夏之交后，被视为最应该被压抑的东西。二次元的代表，动漫游，前两者不能产生多少税收，基本就是上不了台面的，游戏能挣钱能做成产业，但仍然是主流媒体的眼中钉，从魔兽世界到王者荣耀，谁火就要灭谁。当备受钳制的主流文化不能吸引年轻人时，年轻人自然会转向亚文化，当亚文化被挤压边缘化时，年轻人只能走向新兴的相对自由的互联网行业去寻求认同。即使是在欧美，情况也是如此，拿大家喜欢开玩笑的女装大佬来说，Rails 的核心开发者 Aaron Patterson 就是一个，Google 重点项目 Tensorflow 的核心开发者之一，苹果 Swift 语言的核心开发者之一，都是 LGBT 里的 T。这么看起来，女装写代码效率高可能并不是玩笑话。但仔细想想，这其实是社会的悲哀，这些绝顶聪明的人物，在其它主流行业是很难获得足够的认同和发展机会的。","create_at":1499689848},{"id":4530734,"topic_id":375511,"commenter":"starvedcat","thank_count":45,"no":19,"topic_title":"听说 @Devmingwang 去旅游了","content":"@vttc #12 应你妈逼该","create_at":1500095357},{"id":4520738,"topic_id":374824,"commenter":"learnshare","thank_count":42,"no":1,"topic_title":"步入社会，一些事情和疑问必须要问出来，否则无心敲代码","content":"写代码之前，需要先掌握 Markdown，否则别人无心看你的帖子\nhttp://xianbai.me/learn-md/","create_at":1499848695},{"id":4577760,"topic_id":378662,"commenter":"koor","thank_count":41,"no":1,"topic_title":"女孩仰天大笑，你喜欢吗？","content":"看脸","create_at":1501231640},{"id":4575981,"topic_id":378532,"commenter":"mlhorizon","thank_count":41,"no":4,"topic_title":"为什么同事喜欢每五分钟咳嗽一次，反感。","content":"听到别人频繁咳嗽难道不是想着人家是不是生病了，去关心一下吗？\n人与人之间的关怀哪去了？","create_at":1501208755},{"id":4513301,"topic_id":374280,"commenter":"imn1","thank_count":40,"no":15,"topic_title":"大家来看看这种 HR 是不是该开除？因为员工私生活私下改变绩效","content":"以前有一同事，不跟我一个部门，不太熟\n他的事跟顶楼所写几乎完全一样，领导也对他特别关照，听说他部门的同事都非常鄙视他，他也一句反驳的话都没有\n最终他和新女友在公司被说得呆不下去了，领导还热心地给他俩写了介绍信给下家，赞扬他们的工作态度\n两人走后，在年终聚餐时，领导叹了口气说的一句话，全场静默\n“唉……你们啊……他自从知道老婆生的孩子不是他的，就一直加班没回过家”\n旁观者，未必清","create_at":1499676152},{"id":4527408,"topic_id":375275,"commenter":"allenlee7c9","thank_count":37,"no":23,"topic_title":"大家都来说说你最喜欢的名人名言","content":"我不同意你说的话，所以我打算不让你说话 --- 习","create_at":1500004342},{"id":4498985,"topic_id":373389,"commenter":"stephenyin","thank_count":37,"no":7,"topic_title":"Linux 笔记本求推荐（预算 5000 左右）","content":"v 站的 mac 党真是不能忍啊. LZ 提的问题如此明确也能强推 mac, 服~","create_at":1499306563},{"id":4498754,"topic_id":373383,"commenter":"luchenqun","thank_count":37,"no":1,"topic_title":"为什么跳槽往往意味着加薪？","content":"补充一个笑话：A 程序员和 B 程序员，B 程序员提出离职，于是老板重新招聘，以高出 A 程序员原工资 30%的代价，通过猎头挖到 A 程序员，老板觉得挖到宝，窃喜！在 B 程序员和 A 程序员交接的时候，A 程序员觉得 B 程序员不错，于是推荐他到自己的原公司顶替自己的原岗位，B 程序员顺利通过面试入职，薪资提升 50%，A 和 B 通过互换的方式提高了彼此的薪资，两家老板都觉得很满意，原岗位原职责全部不变。\n觉得不是笑话的点一下感谢。。。","create_at":1499304425},{"id":4584828,"topic_id":379135,"commenter":"greenskinmonster","thank_count":35,"no":6,"topic_title":"大家来说说，墙升级是不是在开倒车！？本人观点，不是。。","content":"不能说开倒车的时候没轧到你就不是开倒车。","create_at":1501463758},{"id":4544452,"topic_id":376494,"commenter":"maninshanghai","thank_count":35,"no":5,"topic_title":"真断网了这些矿场咋办，比特币也要分成我国币和外国币了吧","content":"@crab 到这地步了还不忘爱国，真是爱国爱到家了","create_at":1500463225},{"id":4554725,"topic_id":377174,"commenter":"shoaly","thank_count":34,"no":1,"topic_title":"大家平时骑自行车一定要注意","content":"猥琐发育, 别浪","create_at":1500698544},{"id":4514043,"topic_id":374358,"commenter":"bukip","thank_count":31,"no":3,"topic_title":"有哪些东西小时候非常喜欢，现在却买不到了？","content":"爷爷","create_at":1499692097},{"id":4511840,"topic_id":374201,"commenter":"strongcoder","thank_count":31,"no":2,"topic_title":"感觉我们公司测试真能测试，写一个小功能都可以提出 57 个 bug...","content":"等会测试过来发帖子\n\"感觉我们开发技术真搓，写一个小功能都能写出 57 个 bug...\"","create_at":1499655757},{"id":4508446,"topic_id":374001,"commenter":"Weny","thank_count":31,"no":4,"topic_title":"淘宝把我的账户判定为“存在严重被盗迹象”，反馈后竟然要求提交户口本进行验证。","content":"阿里就差挖用户祖坟了","create_at":1499528902},{"id":4512728,"topic_id":374258,"commenter":"fyibmsd","thank_count":30,"no":1,"topic_title":"这种明目张胆的盗版书 Github repo 怎么怼","content":"当然是选择 clone 它了","create_at":1499668804},{"id":4582610,"topic_id":378982,"commenter":"johnlui","thank_count":29,"no":14,"topic_title":"有去看战狼 2 的吗？今天去看了下 感觉很值！","content":"看九楼，我对 v2 表示担忧。","create_at":1501393018},{"id":4572031,"topic_id":378270,"commenter":"SuperMild","thank_count":29,"no":25,"topic_title":"发现舍友使用手机信号干扰器该怎么破？","content":"“建业，那天停电，我发现手机信号变好了，后来我单独关了你房间的电，发现信号也变好了，我怀疑……”\n建业心想，你知道得太多了，表面上却不露声色，挤出一个笑容说：“是吗，可能我房间哪个电器有干扰，你进来一起看看……站着干嘛，进来进来。”\n大明犹豫了一下，虽然依稀感到一丝不知道从何而来的不安，但还是跟在建业后面走进了房间。\n大明的背影渐渐没入幽暗的房间内，明明没有人去碰房门，房门却缓缓关上了……","create_at":1501124365},{"id":4499690,"topic_id":373418,"commenter":"Jacky001","thank_count":29,"no":18,"topic_title":"在线大学生一枚，设计了一个社交软件，市场潜在用户至少 5000 万，欲寻有兴趣的人发现，新人一枚，如有言语不当，望谅解","content":"lz 别听 ls 上的人说，其实你有一条靠谱的路子，把你的 idea 写成一个 ppt，然后带着 ppt 去找投资人，加上你又是大学生，拿个投资还是挺轻松的，拿到投资后，再把 ls 这些人给招到公司里，天天让他们干活，我这点子绝对靠谱，你要不是大学生，我还不会告诉你呢。","create_at":1499314316},{"id":4521029,"topic_id":374826,"commenter":"starvedcat","thank_count":28,"no":26,"topic_title":"大家如何看待学校宿舍没有空调，今天母校在知乎火了一把","content":"放在正常国家：\n1. 学校不会有什么学生必须住宿舍的规定\n2. 学校经费会用在该用的地方\n3. 言论自由，不存在校方出面要求删帖、找出发帖者并给予维稳这样的事情\n4. 人至少会有正常的人类共情。什么“学校没有义务提供空调”“我以前读书时候没空调还不是照样过来了”这种令人作呕的屁话根本就不会出现","create_at":1499852945},{"id":4487914,"topic_id":372643,"commenter":"Goheing","thank_count":28,"no":1,"topic_title":"朋友去台湾旅游了，有没有什么好货可以带回来的。","content":"就让你朋友好好的旅游不行吗?","create_at":1499056521},{"id":4492860,"topic_id":372995,"commenter":"cxbig","thank_count":26,"no":1,"topic_title":"在办公室用青轴的是什么心态？","content":"用什么键盘是我的自由\n那些说三道四的人多半心态不正常","create_at":1499159193},{"id":4551973,"topic_id":376998,"commenter":"luban","thank_count":25,"no":2,"topic_title":"被大学文凭拉低了薪资","content":"说吧，哪个培训班，我去培训还不行吗","create_at":1500621085},{"id":4536779,"topic_id":375934,"commenter":"zhihy123","thank_count":25,"no":5,"topic_title":"除了沉浸代码兴趣之中, 还有其它什么兴趣爱好?","content":"女装，捂脸，逃~","create_at":1500283322},{"id":4532697,"topic_id":375669,"commenter":"zhenghuiy","thank_count":25,"no":16,"topic_title":"[长的好看] ，对于找开软件发相关的工作有帮助吗？","content":"“形象这么好，你还懂开发啊？” 对面热情的 HR 露出笑容。\n“哈哈，也没那么好啦，祖传的。” X 谦虚得回了句，内心却翻滚不停。她是不是看上我了，好几个人都那么说一定是真的，难道我真是人见人爱花见花开的超级帅哥？她其实还蛮好看的。。\n“我们非常欢迎您这种能力强气质佳的程序员来我们公司，能跟这么帅气的程序员共事想想都觉得幸福呢。”\n“哈哈，我也觉得你挺好的。。啊不，你们公司挺好的。”\n“那行，offer 我会 email 给你，一定要接受哦。我这边还有下一个面试，恕不远送啦。” HR 一边说着一边起身替 X 开门。\n“哦哦，我会的。。” X 心中有些疑虑，似乎还没谈工资？但既然已经到了这份上，也就走了出去。\n走到半路发现手机拉在刚刚的会议室了，急忙又回去。\n走到会议室门口，只听到会议室传出一个甜美的声音，“形象那么好，你还懂开发啊？”","create_at":1500172911},{"id":4530245,"topic_id":375484,"commenter":"Jimrussell","thank_count":25,"no":2,"topic_title":"如何优雅地侵犯别人的隐私","content":"666，你不仅不该发火，而且应该请客全部门的人吃饭。\nhttps://www.zhihu.com/question/60347845/answer/186947453","create_at":1500081967},{"id":4524128,"topic_id":375039,"commenter":"bibizhang","thank_count":25,"no":40,"topic_title":"突然想到一个问题，怎么样才能把 V 站搞崩。","content":"","create_at":1499927719},{"id":4561652,"topic_id":377609,"commenter":"binux","thank_count":24,"no":1,"topic_title":"突发奇想，都知道二进制。。用二进制撸个可执行的 helloworld。人力是否可行？","content":"想得太多，书读得太少","create_at":1500886893},{"id":4554446,"topic_id":377158,"commenter":"jellybool","thank_count":24,"no":9,"topic_title":"UCloud 关于 Laravist 社区事件的说明","content":"至始至终，在活动开始或者在跟我对接期间都没有提及\"有效注册用户\"的概念，\"有效注册用户\"按常规理解，就应当是正常注册的、信息真实有效的用户。而且你方在 v 站的帖子也说明得很清楚：**从社区渠道引入的 UCloud 有效注册用户，均可获得 100 元 UCloud 云服务代金券 奖励**,那请问，那些从 laravist 推荐过来的用户获得了 100 代金券算什么呢？\n你 ucloud 今天能把\"有效注册用户\"耍赖成\"至少充值 0.01 元的用户\"，明天就可以耍赖成\"使用了云主机一年以上的用户\"，后天就可以耍赖成\"充值 5000 以上的用户\"。我太年轻，花精力花我自己的资源以录制的新旧视频为代价，帮你推广，你们就毫无规则可言，觉得推广效果不好随意修改规则。\n请问，互联网站长和广告主，有几个签过合同？难道各种数据可以随便改，是否有效点击可以随意说了算么？今天 CPM 说点击一次就有效，明天变成点击注册才有效，后天变成点击注册并且购物了才有效？","create_at":1500694355},{"id":4501069,"topic_id":373532,"commenter":"SourceMan","thank_count":24,"no":1,"topic_title":"工作 10 年写不好一封邮件？","content":"来来来，各位运营看好了\n这个就是最典型的负面营销的案例\n谁要给我犯这个错误，就统统给我滚蛋","create_at":1499332821},{"id":4584849,"topic_id":379135,"commenter":"terence4444","thank_count":23,"no":11,"topic_title":"大家来说说，墙升级是不是在开倒车！？本人观点，不是。。","content":"你只是在特定技术上有优势而已，这就产生优越感了？\n世界上那么多国家都没有 Q，没有网络技术的人被忽悠了吗？\n你认为别人是炮灰，但其实抱着你这样思想自我阉割的已经是炮灰了。","create_at":1501463917},{"id":4540200,"topic_id":376181,"commenter":"kamen","thank_count":23,"no":1,"topic_title":"不一样的日经帖 — 耐操的安卓机","content":"买和 iphone 一样贵的手机\n我最讨厌某些用着几百块的安卓，然后说手机卡的人","create_at":1500363709},{"id":4503917,"topic_id":373699,"commenter":"zuolan","thank_count":23,"no":5,"topic_title":"我这挖坑技术，难道上辈子是地鼠？","content":"程序员博客大都是这样：\n第 x 天：《发布一个新的博客系统 /主题》\n第 xx 天：《 xxxx 博客系统 /主题 2.0 发布》\n第 xxx 天：《博客搬家啦》","create_at":1499405315},{"id":4498627,"topic_id":373376,"commenter":"ywgx","thank_count":23,"no":7,"topic_title":"每天坐在我工位对面和旁边的 2 个同事吃味道大的早饭，怎么办？","content":"别太矫情，都是同事，理解一下吧","create_at":1499303221},{"id":4572304,"topic_id":378264,"commenter":"ETiV","thank_count":22,"no":4,"topic_title":"感觉自己好穷。。。只能努力工作","content":"来个毒鸡汤\n你的努力工作只会让老板更富有","create_at":1501127236},{"id":4552890,"topic_id":377051,"commenter":"PP","thank_count":22,"no":71,"topic_title":"关于 UCloud 赖账的 10 万 推广费，想请大家评评理","content":"这件事情可能并不复杂。\n类似“ UCloud 拥有最终解释权”的说法在此事上基本没有任何法律意义，并且由于 UCloud 在合约关系中属于强势方，法院在审理过程中对于歧义的解释与判断会偏向弱势方。\n关于“有效注册用户”的理解，我认为不难判断。根据 t/359730 中“ UCloud 渠道客户引入计划”第 1 条内容——“赞助期内，从社区渠道引入的 UCloud 有效注册用户，均可获得 100 元 UCloud 云服务代金券奖励；”可以确定所有“从社区渠道引入”的“ UCloud 有效注册用户”未必一定会“获得 100 元 UCloud 云服务代金券”，但是所有“从社区渠道引入”的“获得 100 元 UCloud 云服务代金券”的用户一定被定义为“ UCloud 有效注册用户”。简单明了。\n所以，UCloud 需要举证从未给任何一位未“哪怕是充值一分钱”的“社区渠道引入”用户发送 100 元代金券，否则法理将全在楼主那边，贵司很难有机会。\n同时，建议楼主搜集汇总相关证据，无论是私下和解还是进入诉讼程序，您都会需要这些东西。另外需要提请楼主注意的是，如果您打算借助社区的力量，那么后续怂也好刚也好，都要有头有尾，事毕要给社区一个完整的交代。\n感觉此例可能会成为我商业伦理研究的一个小范本，希望楼主和 UCloud 能够友好解决此事。","create_at":1500633837},{"id":4551917,"topic_id":376941,"commenter":"bluexsky","thank_count":22,"no":17,"topic_title":"有外企收到中国电信限制威皮恩使用的信了吗？","content":"如果中国准备硬扛外企撤出中国的后果,那可以这样执行,没问题的.\n公司早就想搬去东南亚,泰国越南或新加坡了.只是基于搬迁成本和员工安置.\n如果没有 VPN 线路,基本的业务就完全无法开展了,公司搬迁就势在必行,员工可以选择拿遣散费或者跟随公司去国外工作.\n国家无论怎么做都支持,反正要死大家一起死,没什么大不了的.没网络没电视没手机,甚至一到晚上就断电的日子,也不会过不下去,早请示晚汇报八个样板戏,随时揭发身边的反革命分子,定期批斗领导什么的,老一辈玩得转,我们也可以的.\n生在这个年代是一种奇妙的经历.","create_at":1500620257},{"id":4518481,"topic_id":374638,"commenter":"Observer42","thank_count":22,"no":44,"topic_title":"很讨厌那种站电梯上挡住路的人","content":"@terence4444 香港加拿大不再提倡也是怕担责宁可牺牲效率么？\n日本没事故？ Japan's Consumer Affairs Agency 表示东京 2011 年到 2013 年 3865 人在扶梯上受伤送医\n日本几年前也搞过个 no-walk 运动：电梯上不走动\nhttps://www.washingtonpost.com/news/worldviews/wp/2015/08/26/a-japanese-campaign-wants-to-rewrite-the-global-rules-of-escalator-etiquette/?utm_term=.fe78b6a32733\nThe Yomiuri Shimbun reports that 51 railway operators and airport-related companies have banded together to support the no-walk campaign. “ The number of accidents decreases during the campaign period but the practice of keeping one side open is strongly rooted,\"\n期间事故率降低了，但习惯改不了而已“ the practice of keeping one side open is strongly rooted ”\n英国也试过\n“ Escalator etiquette is also under threat in Britain, where operators of the London Tube have come to the same conclusion about user preferences as their Chinese counterparts: more people stand than walk. Rather than worrying about wear-and-tear, however, their plan to end the stand-right, walk-left habit is meant to increase throughput; standing on both sides of an escalator allows for a possible 30 percent increase in total capacity.”\nthroughput 提升了 30\n真要效率，走楼梯快多了，挤什么扶梯\n现在不过是习惯难改而且和道德绑定了而已。","create_at":1499795906},{"id":4544623,"topic_id":376494,"commenter":"dallaslu","thank_count":21,"no":27,"topic_title":"真断网了这些矿场咋办，比特币也要分成我国币和外国币了吧","content":"一个「你」字，V 站上都能扯上十几层楼。\n本来这是一种调侃，比如三表哥常用「贵国」「猩猩」等词汇调侃社会和读者，Twitter 上也有腿叔常说「你推」。生活里也很常见啊，儿子闯了祸，妈妈跟爸爸说能不能管管你儿子；双胞胎哥哥给弟弟送去一台电脑，弟弟问出的钱，哥哥回答说你亲爹给你买的。拿外交甚至家常的词汇——你 /贵 /令，在与有共同归属的人对话中使用，强调对方归属、淡化自己归属，带点讽刺、失望或艳羡的情绪。\n别人讲一个你字，没必要就觉得伤了晶莹剔透的爱国玻璃心。比特币是一个技术改变世界的奇迹，若真的因为政治需要的断网而导致分叉，一颗颗没那么晶莹剔透和脆弱的科技赤子心，多多少少也要碎那么一些吧。如果有的选，我会站在正常币的那一边。","create_at":1500466952},{"id":4540833,"topic_id":376232,"commenter":"wy315700","thank_count":21,"no":5,"topic_title":"突然有一种想法。。“浪费水”究竟指的是什么？水龙头一直开着放水留进管道算是浪费么，但是这样水不一样在整个大环境中么？水费账单中也有“水循环处理过滤费”。这样来说是不是根本就不存在“浪费水”这种说法","content":"熵增大了","create_at":1500374176},{"id":4509454,"topic_id":374058,"commenter":"ovear","thank_count":21,"no":2,"topic_title":"Google 开始作恶了吗","content":"都作恶多少年了。。","create_at":1499575800},{"id":4563098,"topic_id":377693,"commenter":"ivechan","thank_count":20,"no":2,"topic_title":"Python 为什么越来越火了？","content":"不同意人工智能给了 Python 第二春的说法, Python 一直处于秋天, 无论过去还是现在.\n因为 Python 是辅助工具, 是辅助你的, 它更多的是作为第二工具存在的, 所以才显得它流行度那么高.\n(因为大部分人的第一选择是不一样的, 但是很多人的第二工具是 Python )\n比如你搞科研, 那么 Python 是你做科学计算的工具, 画图表的工具, 但你的第一技能还是你的科研能力.\n你搞 AI, 那么 Python 是你设计\"网络\"的工具, 你的第一技能还是你 AI 知识(比如数学, 概率论, 甚至想象力都比 Python 更重要 ), 你做运维, 那么那些 Shell 命令, 网络知识才是你的第一技能. 再举一个例子, 现在网络上用 Python 做的的爬虫非常多, 但是爬虫的首要技能是什么? 那肯定是 HTTP 协议, HTML\\CSS\\JS, 再加点 浏览器和后端开发的基础知识. (小工具可能用不到)\n目前人工智能是很火没错, 但是现在人工智能带动了 Python 完全是某些利益者(出版社, 出书的作者, 培训机构) 宣传的噱头而已.为什么? 因为用其他语言你看不懂, 自然卖不到钱. 比如我连概率论基础知识都不懂, 我按照书里敲敲代码就能\n开发一个 深度学习 系统, 我当然觉得自己吊. 换成 C++呢? 也许因为某一行 for 下面多了一行分号; 就导致编译不通过,\n这样怎么能忽悠到我呢?\n另外你几乎看不到哪家 AI 公司会所谓 Python 工程师这样的岗位招聘 ( Python 岗位多半存在与互联网 Web 开发中). 这也是为什么我说 AI 没有给 Python 第二春的最重要的原因, 因为人工智能是不会催生出 Python 工程师的.\n相反, 人工智能会催生更多 Java/PHP/JS 程序员, 比如说 腾讯阿里的\"黄图检测\", 难道非得一个 Python 程序员才能对接这些 API?","create_at":1500916095},{"id":4562340,"topic_id":377664,"commenter":"shierji","thank_count":20,"no":5,"topic_title":"某 wa 数字又在搞大新闻了-某个很火东西的被动检测","content":"我真心觉得她神烦……","create_at":1500898429},{"id":4556415,"topic_id":377275,"commenter":"j137tt736CExzlfM","thank_count":20,"no":4,"topic_title":"终于和解了《Laravist 社区与 UCloud 的联合声明》","content":"这两位炒作真是够厉害的！！ block","create_at":1500736701},{"id":4531611,"topic_id":375594,"commenter":"tigerstudent","thank_count":20,"no":8,"topic_title":"我们在寻找并肩战斗的小伙伴(非 985、211 づ。◕‿‿◕。慎入)","content":"作为一个非 985 211 毕业的地球人，误点本帖，谨向楼主道歉。","create_at":1500121383},{"id":4526615,"topic_id":375224,"commenter":"Famio","thank_count":20,"no":18,"topic_title":"程序员创业启动资金怎么解决？","content":"最烦不理题意而嘲讽的人。\n1：千万不要用信用卡 /网贷之类的来做启动资金，记住你是负资产创业，信用卡和网贷的坑只会越填越大。\n2：找当地的信用社 or 农商行之类咨询是否有低息的创业贷。\n3：省吃俭用 1 个月，上众包之类的平台上花点小钱请人做个 UI，再加上自己搞个 demo，另有说明 PPT。\n4：找当地的 IT 俱乐部，奉上你的 demo 进行游说。（据我所知，各地各区域都有类似的 IT 俱乐部，其中大部分成员都是企业 or 乙方的 CTO，我常熟这边的俱乐部和上海，北京，武汉等地有过交流）拓展人脉并发掘你的伯乐。\n5：资金到位后（即便是小部分），也要在周期内有阶段性进展让你的投资人了解到你是在认真做事，这是为了立足。\n我以前搞过微信餐饮，后来垮了。","create_at":1499995462},{"id":4509753,"topic_id":374058,"commenter":"beimenjun","thank_count":20,"no":39,"topic_title":"Google 开始作恶了吗","content":"给不想看英文的整理下大概发生了什么破事。\n川普发了个“暴揍 CNN ” gif 的推。\n推特转发点赞数十万。\ngif 原作者 A 君，其实川普发的似乎是别人高清重制 A 君原视频，发现总统发了这个图非常荣幸。\n==========此部分事件顺序比较乱，稍微看了下没看出究竟是什么顺序==========\nCNN 有记者开始联系了 A 君。\n记者也发现 A 君有各类歧视性的言论。\nA 君发现好像事情大了，开始删自己之前的帖子。\nA 君和 CNN 的联系上了。（谁联系谁有不同说法）\n====================\nCNN 很高兴的对外宣布 gif 原作者已经认识到自己的错误了，只要不再犯，他们也就不会追究了。\n然后推特就炸锅了。#CNNBlackMail 之类的。\n传出 A 君是个 15 岁少年的消息，刺激消息的传播。（其实 A 君是个中年人）\nA 君发文为自己之前的言论道歉，表示自己生活中不是网上所发言的具有种族歧视之类倾向的人。\n再接下来就是什么“推特维护 CNN ”啦，“ Google 维护 CNN ”，“打电话要求机场不播 CNN ”之类一些川普粉丝（小粉川？）很喜欢的阶段了。\n实话讲，我对这次两个美国总统候选人和粉丝真的都不太感冒，而且什么 “ XX 维护 CNN ”之类的更是无感，只要不站出来正面刚，都可以说是在维护 CNN 呢。而且对“差评”这类数据，接触不到真实数据，也没有什么站得住脚的逻辑推理，我没有帖子里一些人那么大的兴趣摇旗呐喊：“ Google 作恶维护 CNN ”或者“ Google 只是清理垃圾数据”。\n但是噼里啪啦打了这么一大堆字，我觉得我还是对于怼一些人充满着热情，尤其是事情不一定搞清楚就说“天下乌鸦一般黑”的家伙们。","create_at":1499583226},{"id":4505841,"topic_id":373825,"commenter":"Kilerd","thank_count":20,"no":8,"topic_title":"过期减肥药杀死了一棵树，我该怎么拯救它？","content":"有那么一刻，我觉得家里的小主人已经长大了，家里也就只有主人夫妇陪着我了。\n这些年来，我一直都没有忘记。\n十多年前，主人带着小主人来到市场的那一幕。\n那时候，我们互相还不认识。\n记忆是从一句话开始的：“爸爸，要不我们就买这一株回去种吧”\n在一个男子的点头和同伴们羡慕的眼光下，我被打包了起来。\n那个时候，每次同伴被带走都会掀起一阵羡慕，毕竟宽敞的环境是每一株树苗的唯一渴望。\n我从来没想过幸福会离我那么近。\n虽然被装起来的那段时间是痛苦的，令人窒息的。\n但是我心里满满都是幸福，从来没有那么一刻，如此强烈地渴望和期盼我的新家。\n那个男子和男孩成了我的依托。\n为他们遮阳避雨。\n他们一家人在我的身下乘凉聊天的幕幕我都清晰的记得。\n每当主人讲笑话逗小主人笑时，小主人都会很开心的样子。\n我甚至也摆动我的身躯来附和他们，\n但是他们似乎也没有在意到这点。\n我以为我只是他们人生的一个过客。\n但是我发现我错了。\n那天，风雨交加。我在外面瑟瑟发抖。\n终于我支撑不住了，要倒了下来。\n我以为我最这么离开了。\n在我合上眼之际，我隐约看到了他和他从家里冲了出来。\n之后的事情我不太记得了，唯一知道的就是我知道我没有离开的原因是因为他们。\n我很高兴，这让我更加热情地做好我自己。\n但是，最近，小主人往我身上倒了些什么水。\n我的身体状态开始慢慢变差。\n我从来没有遇到过这种情况。\n从那天起，我一直都在想我做错了什么。\n可是我真的不知道啊。\n或许是不是有一株新的树苗要来代替我了？\n如果是，\n请在临走前再让我看你一眼。\n------- 树。\n以上文字纯属虚构，如有雷同。\n喂，妖妖零吗？ 这里有人。。啊。不，有树成精了。","create_at":1499441783},{"id":4496677,"topic_id":373247,"commenter":"firefox12","thank_count":20,"no":5,"topic_title":"大外企技术荒废的也能很容易进 BAT 吗？","content":"这是因为 外企的业务要求造成的，因为你不知道 他不需要理解 equal 和 hashcode, 但是他负责的业务可能出奇的复杂，从 10 年前的功能到现在的功能都会支持，各种不同的版本，每个业务本事都不复杂，复杂的是如何安排好它们。 其次，整个系统可能有严格的 底层框架和 编写规范，所有人都必须按照这个框架写，这个框架 你根本没听说过，也没开过源，你怎么问？这套框架也许也是起源于 10 年前，无数补丁，但是它上面跑的业务 每年为公司赚着几亿美金的收入，技术落后 代码简单又如何，商业软件很多都这样。每个大公司里的程序员都是颗螺丝钉，把自己的一亩三分地 挖地三十尺。\n我想到了一个故事，当年秦桧府里的包子是天下最好吃的，一个书生娶了一个秦桧府里的厨娘，很高兴，就让他老婆做一次包子，想享受一下 这个天下最好吃的包子。结果他老婆说 做不了，秦府里做包子有 30 道工序，我只负责切葱。 外企的人基本也就是这样吧。不过越是大的公司越是有这样的问题，你现在去 tx 的微信，你就能知道微信的所有架构了？只怕不行","create_at":1499244452},{"id":4555442,"topic_id":377158,"commenter":"PP","thank_count":19,"no":235,"topic_title":"UCloud 关于 Laravist 社区事件的说明","content":"在 V 友 @jellybool 先生发布的 t/377051 主题下，我明确提出，“兼听则明，如果 UCloud 愿意提出自己的观点或证据，相信所有理性的 V 友都会欢迎。”现在见到 UCloud 发布了此则《说明》，很高兴 UCloud 作出了回应。\n今日 UCloud 发布了此则《说明》，令人非常重视。反复通读、掂量之下，在为 UCloud 没有回避问题感到欣许的同时，也为 UCloud 没有直面责任等做法而感到非常遗憾。\n论无据不立，下面我根据贵司所发布的《说明》的具体内容依次将我认为存疑或异议之处阐述出来，欢迎贵司及众 V 友们指证、交流。\n1 关于《说明》中开端的“初心”部分\n商业计划必然有其背景与动机，在此时此刻，与其描述美好愿景，不如翔实的介绍此计划案的制定与执行细节。贵司在 V 站日久，相信多少知晓“请给云计算一点宽容”这个梗的由来，前车之鉴在此。不妨在贵司内部寻一位对文字敏感的人士，相信他 /她会明白我在说什么。\n2 对于“事件始末”的深究\n贵司称“ 2017 年 05 月 08 日，Laravist 创始人联系到我方……希望参加渠道客户引入计划，获得渠道返现。”\n为何不见贵司描述当时是如何回应的？\n贵司称“ Laravist 创始人在自己的社区，以合作之名上线了一个社区活动。”\n是否贵司认为同 Laravist 创始人在商议合作之初曾经对相关推广活动提出过相关指导性意见或文件？\n贵司又称“作为合作方，UCloud 并未收到任何通知。”\n这就奇怪了，一会儿是一会儿不是，中间仅隔了一句话就来了个大变样，那么 Laravist 创始人到底是不是你们的合作方呢？\n贵司称“因为活动本身存在明显的诱导注册行为”\n如果贵司方便的话，是否可以说明“活动本身”是指什么？是指 UCloud 的活动还是指 Laravist 创始人的活动？要小心哦，“明显的诱导注册行为”这几个字可能涉嫌诽谤哦！\n多两句嘴。文字暗示是个很高级的技能，但是用不好是会付出代价的，特别是一些下三滥的抹黑行为。这种行径同贵司的君子“初心”不大和谐，小心精神分裂。\n贵司称“在 UCloud 不知情的情况下，做了大量推广。”\n这些“ UCloud 不知情”之类的话就不要再提了，不专业，徒增笑料。\n贵司称“这部分用户均来自 laravist 社区……并无云服务相关的需求。”\n这很离谱，俨然贵司业务完全不需免费用户向付费用户转换这一过程，实现了对人类商业活动规律的实施史诗级突破，连续拿 100 界诺贝尔经济学奖都不足以表彰贵司的巨大贡献。\n贵司亦提及“为了获得 laravist 社区的免费视频”\n羞辱一整个社区，如此不智，贵司想好后果了吗？\n贵司指出“ 2017 年 05 月 17 日上午 11:00，我方……希望叫停此活动”及“经过沟通，双方电话达成一致，活动可以继续。”\n若贵司所言均属实，则可以由此得出几点认识：\na 5 月 17 日之前发生的所有注册用户默认有效；\nb 5 月 17 日之后来自该社区宣传渠道的注册用户确认有效；\nc 双方协作于 5 月 17 日之后促进付费用户转化率的提升，但 Laravist 创始人仅对分母负责；\nd 至于“ 2.87%”这个数字，无论其是否准确与合理，分子由贵司负责，与 Laravist 创始人无关；\ne 至 6 月 22 日，实际产生的“有效注册用户”数量应为 5 月 17 日前全部关联注册用户加上 5 月 17 日至 6 月 22 日之间 Laravist 社区宣传渠道来源注册用户；\n另外，贵司“ UCloud 渠道客户引入计划”中已将“获得 100 元 UCloud 云服务代金券奖励”同“有效注册用户”作出了直接关联，建议贵司不要再在“有效注册用户”的解释上白费力气。\n3 关于“解决方案”\n对于 V 友 @jellybool 先生同贵司之间的纠纷，始终希望你们双方能够通过友好协商来解决此事。然而根据贵司发布的此则《说明》的具体文字内容，我对贵司解决问题的诚意与善意都存有疑虑。\n此刻，我觉得有必要提醒 V 友 @jellybool 先生，如果 UCloud 方面在发布此则《说明》前就此事及此《说明》同您作出过沟通，哪怕未达成一致，你们双方也存在继续协商的可能；反之，您还是另作准备为好，以解决问题为名单方面发布声明的做法是很说明问题的。\n对于 UCloud 公司，事后废约，贵司守信否？和解反复，贵司负责否？误导抹黑，贵司诚实？见利忘义，商誉一朝尽毁，值否？\n对于几位专门发布长篇回复通过描述自身得益于 UCloud 之帮助来论述 UCloud 之光辉的 V 友，如果诸位对于 UCloud 方面同 Laravist 创始人之间的纠纷有所疑问和见解，建议就事论事，谁对谁错直接讲评举证。站边台、敲边鼓，于事无补，不要做这种糊涂蛋，不合时宜，不合事理。这种做法不是在帮 UCloud，而是在坑 UCloud，拉着 UCloud 一起 LOW，只会进一步激怒社群，不会有任何人会在这些行为后获益。恳切建议有关人士重新考虑自己的言行。","create_at":1500711393},{"id":4554420,"topic_id":377158,"commenter":"bigtan","thank_count":19,"no":4,"topic_title":"UCloud 关于 Laravist 社区事件的说明","content":"还是别吹了吧，玩不起就别玩。我在知乎挂了卖虚拟主机的 aff 链接都不止收到这点钱。","create_at":1500693852},{"id":4548403,"topic_id":376651,"commenter":"momo5269","thank_count":19,"no":5,"topic_title":"问一下，混淆过的协议现在检测率有多少？","content":"抱歉上一张忘记调整宽度了","create_at":1500544080},{"id":4544849,"topic_id":376507,"commenter":"ZRS","thank_count":19,"no":13,"topic_title":"若那艰难的日子真来了，你们还敢用国外的服务吗？","content":"看情况吧\n饭没了的艰难日子里，有吃树皮草根的，但是没有吃屎的","create_at":1500471881},{"id":4540814,"topic_id":376232,"commenter":"RqPS6rhmP3Nyn3Tm","thank_count":19,"no":3,"topic_title":"突然有一种想法。。“浪费水”究竟指的是什么？水龙头一直开着放水留进管道算是浪费么，但是这样水不一样在整个大环境中么？水费账单中也有“水循环处理过滤费”。这样来说是不是根本就不存在“浪费水”这种说法","content":"同理，根据能量守恒原理，世界上怎么会有浪费能源呢？骗局！","create_at":1500373853},{"id":4527466,"topic_id":375275,"commenter":"intel8808","thank_count":19,"no":29,"topic_title":"大家都来说说你最喜欢的名人名言","content":"最近这个形势下天天看到\n如果天空是黑暗的，那就摸黑生存；如果发出声音是危险的，那就保持沉默；如果自觉无力发光的，那就蜷伏于墙角。但不要习惯了黑暗就为黑暗辩护；不要为自己的苟且而得意；不要嘲讽那些比自己更勇敢热情的人们。我们可以卑微如尘土，不可扭曲如蛆虫。——季业","create_at":1500005159},{"id":4503993,"topic_id":373707,"commenter":"grimpil","thank_count":19,"no":1,"topic_title":"其实有两个 iPhone 的话, 就不需要双卡双待手机了","content":"虽然很有道理，但是古人有句话说的挺好的：何不食肉糜？","create_at":1499406107},{"id":4500337,"topic_id":373470,"commenter":"operafans","thank_count":19,"no":6,"topic_title":"七牛和盗版书网站勾结也不管管吗？","content":"QQ 和盗版书网站勾结，给盗版侵权网站提供 QQ 客服服务\n微博和盗版书网站勾结，给盗版侵权网站提供微博宣传服务\n支付宝、微信和盗版书网站勾结，给盗版侵权网站提供支付服务\n360 和盗版书网站勾结，给盗版侵权网站提供网站安全检测服务\nZF 和盗版书网站勾结，给盗版侵权网站提供备案服务\n哇 感觉要赚大发了","create_at":1499323627},{"id":4552657,"topic_id":377051,"commenter":"tar","thank_count":18,"no":6,"topic_title":"关于 UCloud 赖账的 10 万 推广费，想请大家评评理","content":"无意冒犯\n“注册并激活 UCloud 的账号的就是有效用户”就能得 500 块推广费的话，我能刷到他破产","create_at":1500630382},{"id":4532145,"topic_id":375594,"commenter":"AlwaysBee","thank_count":18,"no":35,"topic_title":"我们在寻找并肩战斗的小伙伴(非 985、211 づ。◕‿‿◕。慎入)","content":"大概 2014 年 2 月份给贵司投过简历，当时刚好快毕业找工作，应聘的前端开发，给了两个任务，一个是实现瀑布流、一个是按设计稿实现，像杂志那样的效果，刚开始我是做了后者，你们说 CSS 代码写得太多了，200 多行可以搞定的用了 400 多行，后面让我试试瀑布流，想看看我的 js 代码，并且说不超过 400 行可以搞定，我最终完成是 130 行左右代码，但最终你们还是觉得我不合适，当时还年轻，以为是自己能力不行，现在回过头想想，你们是不是在利用招聘招免费劳动力啊？也许我想多了","create_at":1500134365},{"id":4531528,"topic_id":375594,"commenter":"davy1995","thank_count":18,"no":7,"topic_title":"我们在寻找并肩战斗的小伙伴(非 985、211 づ。◕‿‿◕。慎入)","content":"好好写个 985 211 优先很难？非要写什么非 985 211 慎入....","create_at":1500118316},{"id":4499444,"topic_id":373389,"commenter":"fengxueshangu","thank_count":18,"no":38,"topic_title":"Linux 笔记本求推荐（预算 5000 左右）","content":"不得不说，推荐 MAC 的都是 SB","create_at":1499311156},{"id":4574582,"topic_id":378452,"commenter":"Sharuru","thank_count":17,"no":1,"topic_title":"$$R 结束了?","content":"挺好的。","create_at":1501162106},{"id":4571899,"topic_id":378270,"commenter":"Johnjiong","thank_count":17,"no":1,"topic_title":"发现舍友使用手机信号干扰器该怎么破？","content":"你可能揪出了一个敌特。。。囧","create_at":1501123276},{"id":4559582,"topic_id":377446,"commenter":"zhlssg","thank_count":17,"no":3,"topic_title":"人。为什么要上班！","content":"贫穷让我无法入睡","create_at":1500861362},{"id":4528362,"topic_id":375329,"commenter":"andyL","thank_count":17,"no":18,"topic_title":"这两天各大互联网公司是不是都在急招 AC 自动机工程师？","content":"那张椅子注定等不到来领奖的人","create_at":1500018476},{"id":4514901,"topic_id":374395,"commenter":"yoke123","thank_count":17,"no":25,"topic_title":"麻痹，黑马培训机构的学员写的代码！真爱生命远离培训班！！！","content":"少点冷嘲热讽 多点提醒帮助\n生活不易 且行且珍惜","create_at":1499735089},{"id":4509442,"topic_id":374059,"commenter":"tigerstudent","thank_count":17,"no":1,"topic_title":"OneNote 本土化怎么做的这么烂","content":"别乱讲，人家哪里有什么本土化","create_at":1499575561},{"id":4502632,"topic_id":373635,"commenter":"yunkchen","thank_count":17,"no":1,"topic_title":"公司来了个想总经理,我该何去何从?","content":"如果这不是个段子，那这个总经理就是个段子。","create_at":1499390435},{"id":4554865,"topic_id":377158,"commenter":"Chingim","thank_count":16,"no":139,"topic_title":"UCloud 关于 Laravist 社区事件的说明","content":"@lgn21st 我来翻译一下: 你们知道 ucloud 有多努力吗？","create_at":1500700486},{"id":4550124,"topic_id":376868,"commenter":"stephenyin","thank_count":16,"no":15,"topic_title":"有一个白痴问题，我忘记了这个账号名是什么含义了？","content":"焚化炉,一会去.","create_at":1500601533},{"id":4527171,"topic_id":375275,"commenter":"DrJoseph","thank_count":16,"no":5,"topic_title":"大家都来说说你最喜欢的名人名言","content":"\"打工是不可能打工的,这辈子都不可能打工,做生意又不会，就是逛 V2 才能打发时间这样子,在 V2 的感觉就像回家一样,比家里面好多了,里面个个都是人才,说话又好听，我超喜欢里面的\" ——鸠斯劳兹朔德","create_at":1500001532},{"id":4520773,"topic_id":374824,"commenter":"anyele","thank_count":16,"no":4,"topic_title":"步入社会，一些事情和疑问必须要问出来，否则无心敲代码","content":"别想多了, 这么高的房价和生活成本就是让你好好工作, 别想这些,没用的, 不然等你啥都有了你就想着自由平等民主, 那时候赵家人就头疼了","create_at":1499849187},{"id":4501239,"topic_id":373540,"commenter":"stabc","thank_count":16,"no":4,"topic_title":"7 月 6 日是世界接吻日，晚上你还是孤单单地刷 V2EX 么？","content":"求求你别说了","create_at":1499334858},{"id":4485125,"topic_id":372462,"commenter":"mytsing520","thank_count":16,"no":23,"topic_title":"支付宝《花呗》新版合同，让人不寒而栗，都要搜集“手机通话分钟数了”","content":"怕的是你关了花呗后他还在收集这些东西","create_at":1498972025},{"id":4584056,"topic_id":379088,"commenter":"Chingim","thank_count":15,"no":12,"topic_title":"\"同类软件的鼻祖” Seer 抄走了我的 GPL 代码去卖钱……","content":"这种抗争我喜欢, 至少最后不会和对方签保密协议, 然后当做什么都没发生","create_at":1501426296},{"id":4554576,"topic_id":377158,"commenter":"Tunar","thank_count":15,"no":58,"topic_title":"UCloud 关于 Laravist 社区事件的说明","content":"@skyjerry 和解是不可能和解的，这辈子都不可能和解的，有效用户又说不清，只有想出 1000 个用户严重影响服务器，才能忽悠大家这样子，v2 里面的人超好骗，个个都是弱智\n(玩笑，勿对号入座)","create_at":1500696166},{"id":4547748,"topic_id":376651,"commenter":"miaomiao888","thank_count":15,"no":3,"topic_title":"问一下，混淆过的协议现在检测率有多少？","content":"最近各种探测$$的传言乱飞，这种消息无法证伪，但是联通客户端有一个“上网记录”的页面，可以显示用户的上网类型，于是我发动群友做了一下统计，看看各种协议和混淆在联通那里被判为什么，作为参考。从结果看以后 TLS 似乎是标配了。\n如何选择？\n如果你机房的线路非常好（香港、台湾机房）那么直接使用 BBR + SS/SSR 即可。\n如果你机房的线路很差（比如丢包很高或者距离很远）那么可以使用 BBR + SS/SSR + kcptun。\n如果你的运营商会封锁 SS 或者进行 QoS，那么使用 BBR + SSR 混淆，或者 BBR + VMess 的 TLS 混淆。\n联通客户端检测\n软件和协议 联通检测类型 访问网址\nShadowsocks TCP 业务 显示服务器 IP\nSS + http_simple （ 80 端口） 上网 (Web 方式 get) 显示混淆域名\nSSR TCP 业务 显示服务器 IP\nSSR + http_simple 上网 (Web 方式 get) 显示混淆域名\nSSR + TLS(443) * 安全类网页浏览 (HTTPS VPN) 流量\n* HTTPS 链接 显示混淆域名\nSSR + TLS(非 443) * 网络连接（网页）\n* HTTPS 链接 显示混淆域名\nOpenConnect\nIPSec VPN UDP 业务 显示服务器 IP\nV2Ray TCP 业务 显示服务器 IP\nV2Ray + TLS HTTPS 网络连接 显示证书域名\nnghttpx + TLS HTTPS 网络连接 显示证书域名\nkcptun UDP 业务 显示服务器 IP\n链接： https://github.com/waylybaye/HyperApp-Guide/blob/master/zh/GFW.md","create_at":1500534579},{"id":4540649,"topic_id":376218,"commenter":"mpich","thank_count":15,"no":4,"topic_title":"大家怎么看 “这个功能很简单” ？","content":"“这个功能没价值”\n“你怎么知道这个功能没价值？”\n“你怎么知道这个功能很简单？”","create_at":1500370756},{"id":4495532,"topic_id":373176,"commenter":"thinks","thank_count":15,"no":3,"topic_title":"你真的很在意数字里的 4 么？","content":"有本事不用 4G 网络。","create_at":1499228653},{"id":4495384,"topic_id":373168,"commenter":"oktango","thank_count":15,"no":8,"topic_title":"感觉这代 835 的机器好给力","content":"@xx998 云体验师？","create_at":1499226622},{"id":4491327,"topic_id":372880,"commenter":"xss","thank_count":15,"no":1,"topic_title":"港真, 这个年龄和状态, 该出国读个研吗?","content":"劝退个毛, 赶紧去....\n要不然再过几年 30 了, 你就更不愿意折腾了","create_at":1499138980},{"id":4490546,"topic_id":372829,"commenter":"arrow2015","thank_count":15,"no":6,"topic_title":"Klib 到底赚了多少钱？","content":"这么长的文章没有回答标题的问题。理应在第一句回答的。如果这篇文章的问题在 Stackoverflow 上，文章内容作为回答，这个回答应该是负分。","create_at":1499130685},{"id":4486933,"topic_id":372577,"commenter":"ooh","thank_count":15,"no":3,"topic_title":"又是一个低潮期!!!","content":"我猜是通过撸管次数来算的:-D","create_at":1499043324},{"id":4582310,"topic_id":378982,"commenter":"gap","thank_count":14,"no":2,"topic_title":"有去看战狼 2 的吗？今天去看了下 感觉很值！","content":"这次水军覆盖面不错啊，看了预告片就没有看的欲望了","create_at":1501387431},{"id":4574844,"topic_id":378452,"commenter":"taikobo","thank_count":14,"no":35,"topic_title":"$$R 结束了?","content":"@clino 你说的对，但是和这次的事情有一点不同\n首先你觉得不安全了应该向对方提出\n对方不接受你甚至可以写一个小工具证明对方安全的确有问题\n这也是白帽子常做的事情嘛\n但是把自己写的小工具公开到网上你觉得合适吗？\n其次这也不是她第一次这么作了，投票都投了好几次了\n最后原版的作者回应了一个小工具证明她自己造的轮子安全问题严重的多\n结果她先是说“终于有人可以挑战我了，我准备半年的协议可以上了”\n你觉得这是友善提醒的态度还是想把对方踩在脚下的态度？\n然后又说“你写的小工具是错的，我不需要上新协议”\n隔了不到 24 小时，就说自己被人肉了，然后删光\n我是觉得，巧合了一点","create_at":1501167850},{"id":4558115,"topic_id":377369,"commenter":"yoyoyoyo","thank_count":14,"no":2,"topic_title":"如果吵架时女友朝你大声喊 “我花我的钱 怎么了” 你怎么办？","content":"羞涩的回答：下次花我的好不好","create_at":1500804213},{"id":4546101,"topic_id":376578,"commenter":"plqws","thank_count":14,"no":2,"topic_title":"深圳大面积启用精准 SS 协议识别技术有老哥科普下么","content":"ssr 作者那个人品，这种新闻不信也罢","create_at":1500514569},{"id":4533139,"topic_id":375702,"commenter":"KirkZheng","thank_count":14,"no":2,"topic_title":"斯坦福最新项目：重建互联网","content":"把数据储存到手机电脑平板等一切联网的终端上面，魔笛手公司出品。","create_at":1500182838},{"id":4532356,"topic_id":375610,"commenter":"jahosnake","thank_count":14,"no":63,"topic_title":"罗永浩 Big Bang 被指抄袭效仿 Pin","content":"这个问题上我觉得没什么好反转了，还认为锤子抄了的人真的是“非蠢即坏”\n总结一下就是：\n1.pin 作者不认为技术实现上抄袭（事实上分词技术也早说了是三角兽提供的），而是创意抄袭。\n2.朱萧木给出证据证明了创意早已有之并非抄袭。\n3.现在要的是 pin 作者证明自己比锤子更早有这个创意，并且最重要的是，还得证明这个创意在当时通过某种渠道被剽窃到了锤子那。","create_at":1500144928},{"id":4527200,"topic_id":375275,"commenter":"coderluan","thank_count":14,"no":6,"topic_title":"大家都来说说你最喜欢的名人名言","content":"名言什么的，没有啥最喜欢的，一般会随着环境变化，目前的话，是这句：\n起初他们迫害共产党员，我没有说话，因为我不是马克思的信徒。\n后来他们迫害犹太人，我没有说话，因为我是日耳曼人。\n再后来他们迫害天主教徒，我没有说话，因为我是新教牧师。\n最后他们迫害到我头上，我环顾四周，却再也没有人能为我说话。","create_at":1500001815}]}}